{
    "xianshi":[
	  {"id":1,"lujin1":"首页","lujin2":"限时抢购","imgurl":"img/tongshu16.jpeg","imgurl2":"img/tongshulun16.jpeg","xiangqingtu":"img/tongshutu16.jpeg","price":"42.84","prices":"140.00","title":"曹文轩画本5册","zuozhe":"曹文轩","xiaoliang":"2788","kucun":"157","chubanshe":"长江少儿","chubanrqi":"2020-04-01"},
	  {"id":2,"lujin1":"首页","lujin2":"限时抢购","imgurl":"img/renwen7.jpg","imgurl2":"img/renwenlun7.jpg","xiangqingtu":"img/renwentu7.jpg","price":"32.30","prices":"58.00","title":"内在的星空","zuozhe":"余秋雨","xiaoliang":"575","kucun":"187","chubanshe":"北京联合","chubanrqi":"2018-01-23"},
	  {"id":3,"lujin1":"首页","lujin2":"限时抢购","imgurl":"img/renwen15.jpg","imgurl2":"img/renwenlun15.jpg","xiangqingtu":"img/renwentu15.jpg","price":"18.67","prices":"32.00","title":"且以优雅过一生(杨绛传)","zuozhe":"桑妮","xiaoliang":"25860","kucun":"149","chubanshe":"湖南文艺","chubanrqi":"2018-05-12"},
	  {"id":4,"lujin1":"首页","lujin2":"限时抢购","imgurl":"img/tongshu31.jpeg","imgurl2":"img/tongshulun31.jpeg","xiangqingtu":"img/tongshutu31.jpeg","price":"67.88","prices":"175.00","title":"彩虹桥动物母爱绘本(共5册)","zuozhe":"沈石溪","xiaoliang":"344","kucun":"183","chubanshe":"浙江教育","chubanrqi":"2020-10-23"},
	  {"id":5,"lujin1":"首页","lujin2":"限时抢购","imgurl":"img/wenxue24.jpg","imgurl2":"img/wenxuelun24.jpg","xiangqingtu":"img/wenxuetu24.jpg","price":"41.31","prices":"59.00","title":"你当像鸟飞往你的山","zuozhe":"塔拉·韦斯特弗","xiaoliang":"57279","kucun":"7189","chubanshe":"南海","chubanrqi":"2020-09-12"},
	  {"id":6,"lujin1":"首页","lujin2":"限时抢购","imgurl":"img/wenxue11.jpg","imgurl2":"img/wenxuelun11.jpg","xiangqingtu":"img/wenxuetu11.jpg","price":"42.82","prices":"192.00","title":"浪漫古典行（全六册）","zuozhe":"蕴玉","xiaoliang":"1789","kucun":"128","chubanshe":"中国华侨","chubanrqi":"2018-03-17"}
         ],
    "zbtj":[
	  {"id":7,"lujin1":"首页","lujin2":"重磅推荐","fengmian":"img/zhongbang11.jpg","imgurl":"img/tongshu9.jpeg","imgurl2":"img/tongshulun9.jpeg","xiangqingtu":"img/tongshutu9.jpeg","price":"27.65","prices":"39.50","title":"窗边的小豆豆 中小学生课外阅读","zuozhe":"(日)黑柳彻子","xiaoliang":"46793","kucun":"832","chubanshe":"南海","chubanrqi":"2018-06-01"},
	  {"id":8,"lujin1":"首页","lujin2":"重磅推荐","fengmian":"img/zhongbang22.jpg","imgurl":"img/tongshu8.jpeg","imgurl2":"img/tongshulun8.jpeg","xiangqingtu":"img/tongshutu8.jpeg","price":"138.6.","prices":"198.00","title":"你好艺术(共13册)","zuozhe":"(日)结城昌子","xiaoliang":"431","kucun":"57","chubanshe":"中信","chubanrqi":"2020-03-03"},
	  {"id":9,"lujin1":"首页","lujin2":"重磅推荐","fengmian":"img/zhongbang33.jpg","imgurl":"img/tongshu2.jpeg","imgurl2":"img/tongshulun2.jpeg","xiangqingtu":"img/tongshutu2.jpeg","price":"27.86","prices":"39.80","title":"小狗钱钱","zuozhe":"博多·舍费尔","xiaoliang":"43234","kucun":"2136","chubanshe":"中信","chubanrqi":"2021-01-01"},
	  {"id":10,"lujin1":"首页","lujin2":"重磅推荐","fengmian":"img/zhongbang44.jpg","imgurl":"img/wenxue22.jpg","imgurl2":"img/wenxuelun22.jpg","xiangqingtu":"img/wenxuetu22.jpg","price":"38.50","prices":"55.00","title":"人生海海","zuozhe":"麦家","xiaoliang":"13879","kucun":"1168","chubanshe":"北京十月文艺","chubanrqi":"2020-04-21"}
	    ], 
	"xpsd":[
	  {"id":11,"lujin1":"首页","lujin2":"新品速递","fengmian":"img/zhongbang55.jpg","imgurl":"img/wenxue25.jpg","imgurl2":"img/wenxuelun25.jpg","xiangqingtu":"img/wenxuetu25.jpg","price":"29.40","prices":"49.00","title":"心安即是归处","zuozhe":"季羡林","xiaoliang":"767","kucun":"320","chubanshe":"古吴轩","chubanrqi":"2018-02-15"},
	  {"id":12,"lujin1":"首页","lujin2":"新品速递","fengmian":"img/zhongbang66.jpg","imgurl":"img/wenxue2.jpg","imgurl2":"img/wenxuelun2.jpg","xiangqingtu":"img/wenxuetu2.jpg","price":"45.93","prices":"126.40","title":"冰心儿童文学全集共8册","zuozhe":"刘敬余","xiaoliang":"6513","kucun":"267","chubanshe":"北京教育","chubanrqi":"2020-03-10"},
	  {"id":13,"lujin1":"首页","lujin2":"新品速递","fengmian":"img/zhongbang77.jpg","imgurl":"img/wenxue6.jpg","imgurl2":"img/wenxuelun6.jpg","xiangqingtu":"img/wenxuetu6.jpg","price":"148.00","prices":"298.00","title":"老舍作品集（全八册 附书签）","zuozhe":"老舍","xiaoliang":"5875","kucun":"195","chubanshe":"北京联合","chubanrqi":"2020-08-16"},
	  {"id":14,"lujin1":"首页","lujin2":"新品速递","fengmian":"img/zhongbang88.jpg","imgurl":"img/wenxue19.jpg","imgurl2":"img/wenxuelun19.jpg","xiangqingtu":"img/wenxuetu19.jpg","price":"28.50","prices":"38.00","title":"苏菲的世界","zuozhe":"(挪威)乔斯坦·贾德","xiaoliang":"52810","kucun":"7315","chubanshe":"作家","chubanrqi":"2018-03-19"}
	    ], 
	"rxtj":[
	  {"id":15,"lujin1":"首页","lujin2":"热销推荐","fengmian":"img/zhongbang99.jpg","imgurl":"img/renwen3.jpg","imgurl2":"img/renwenlun3.jpg","xiangqingtu":"img/renwentu3.jpg","price":"24.97","prices":"88.00","title":"人生课堂（全三册）","zuozhe":"张洋","xiaoliang":"6675","kucun":"123","chubanshe":"明主与建设","chubanrqi":"2020-05-23"},
	  {"id":16,"lujin1":"首页","lujin2":"热销推荐","fengmian":"img/zhongbang1100.jpg","imgurl":"img/renwen6.jpg","imgurl2":"img/renwenlun6.jpg","xiangqingtu":"img/renwentu6.jpg","price":"26.10","prices":"58.00","title":"极简中国史","zuozhe":"吕思勉","xiaoliang":"9669","kucun":"126","chubanshe":"江苏文艺","chubanrqi":"2019-09-29"},
	  {"id":17,"lujin1":"首页","lujin2":"热销推荐","fengmian":"img/zhongbang1111.jpg","imgurl":"img/renwen20.jpg","imgurl2":"img/renwenlun20.jpg","xiangqingtu":"img/renwentu20.jpg","price":"18.58","prices":"39.80","title":"乌合之众(群体心理研究)","zuozhe":"(法)古斯塔夫·勒庞","xiaoliang":"9734","kucun":"565","chubanshe":"中国友谊","chubanrqi":"2020-12-03"},
	  {"id":18,"lujin1":"首页","lujin2":"热销推荐","fengmian":"img/zhongbang1122.jpg","imgurl":"img/renwen26.jpg","imgurl2":"img/renwenlun26.jpg","xiangqingtu":"img/renwentu26.jpg","price":"16.06","prices":"32.00","title":"断舍离","zuozhe":"(日)山下英子","xiaoliang":"79485","kucun":"566","chubanshe":"广西科技","chubanrqi":"2018-02-17"}
	    ], 
    "retui":[
	  {"id":19,"lujin1":"首页","lujin2":"热门推荐","imgurl":"img/renwen1.jpg","imgurl2":"img/renwenlun1.jpg","xiangqingtu":"img/renwentu1.jpg","price":"32.46","prices":"58.00","title":"中华上下五千年 共3册","zuozhe":"林汉达","xiaoliang":"72731","kucun":"666","chubanshe":"少年儿童","chubanrqi":"2020-04-19"},
	  {"id":20,"lujin1":"首页","lujin2":"热门推荐","imgurl":"img/renwen3.jpg","imgurl2":"img/renwenlun3.jpg","xiangqingtu":"img/renwentu3.jpg","price":"24.97","prices":"88.00","title":"人生课堂（全三册）","zuozhe":"张洋","xiaoliang":"675","kucun":"123","chubanshe":"明主与建设","chubanrqi":"2020-05-23"},
	  {"id":21,"lujin1":"首页","lujin2":"热门推荐","imgurl":"img/renwen5.jpg","imgurl2":"img/renwenlun5.jpg","xiangqingtu":"img/renwentu5.jpg","price":"23.05","prices":"68.00","title":"彩图全解山海经","zuozhe":"(汉)刘向","xiaoliang":"1786","kucun":"141","chubanshe":"中国华侨","chubanrqi":"2019-12-06"},
	  {"id":22,"lujin1":"首页","lujin2":"热门推荐","imgurl":"img/renwen7.jpg","imgurl2":"img/renwenlun7.jpg","xiangqingtu":"img/renwentu7.jpg","price":"32.30","prices":"58.00","title":"内在的星空","zuozhe":"余秋雨","xiaoliang":"575","kucun":"187","chubanshe":"北京联合","chubanrqi":"2018-01-23"},
	  {"id":23,"lujin1":"首页","lujin2":"热门推荐","imgurl":"img/renwen9.jpg","imgurl2":"img/renwenlun9.jpg","xiangqingtu":"img/renwentu9.jpg","price":"21.39","prices":"42.00","title":"半小时漫画科学史","zuozhe":"陈磊","xiaoliang":"4064","kucun":"324","chubanshe":"文汇","chubanrqi":"2018-07-19"},
	  {"id":24,"lujin1":"首页","lujin2":"热门推荐","imgurl":"img/renwen11.jpg","imgurl2":"img/renwenlun11.jpg","xiangqingtu":"img/renwentu11.jpg","price":"76.11","prices":"162.00","title":"民国才女传（套装共4册）","zuozhe":"清心","xiaoliang":"956","kucun":"159","chubanshe":"煤炭工业","chubanrqi":"2020-11-29"},
	  {"id":25,"lujin1":"首页","lujin2":"热门推荐","imgurl":"img/renwen13.jpg","imgurl2":"img/renwenlun13.jpg","xiangqingtu":"img/renwentu13.jpg","price":"18.00","prices":"36.00","title":"亲爱的安德烈","zuozhe":"安德烈","xiaoliang":"159276","kucun":"1321","chubanshe":"广西师大","chubanrqi":"2020-01-21"},
	  {"id":26,"lujin1":"首页","lujin2":"热门推荐","imgurl":"img/renwen15.jpg","imgurl2":"img/renwenlun15.jpg","xiangqingtu":"img/renwentu15.jpg","price":"18.67","prices":"32.00","title":"且以优雅过一生(杨绛传)","zuozhe":"桑妮","xiaoliang":"25860","kucun":"149","chubanshe":"湖南文艺","chubanrqi":"2018-05-12"},
	  {"id":27,"lujin1":"首页","lujin2":"热门推荐","imgurl":"img/renwen17.jpg","imgurl2":"img/renwenlun17.jpg","xiangqingtu":"img/renwentu17.jpg","price":"27.71","prices":"49.90","title":"高效能人士的七个习惯（钻石版）","zuozhe":"（美）史蒂芬","xiaoliang":"67888","kucun":"1880","chubanshe":"中国青年出版社","chubanrqi":"2019-02-17"},
	  {"id":28,"lujin1":"首页","lujin2":"热门推荐","imgurl":"img/renwen19.jpg","imgurl2":"img/renwenlun19.jpg","xiangqingtu":"img/renwentu19.jpg","price":"22.72","prices":"32.00","title":"钝感力","zuozhe":"(日)渡边淳一","xiaoliang":"25304","kucun":"2789","chubanshe":"青岛","chubanrqi":"2018-07-18"},
	  {"id":29,"lujin1":"首页","lujin2":"热门推荐","imgurl":"img/renwen21.jpg","imgurl2":"img/renwenlun21.jpg","xiangqingtu":"img/renwentu21.jpg","price":"21.17","prices":"38.00","title":"蛤蟆先生去看心理医生","zuozhe":"(英)罗伯特·戴博德","xiaoliang":"65088","kucun":"5841","chubanshe":"天津人民","chubanrqi":"2019-07-09"},
	  {"id":30,"lujin1":"首页","lujin2":"热门推荐","imgurl":"img/renwen23.jpg","imgurl2":"img/renwenlun23.jpg","xiangqingtu":"img/renwentu23.jpg","price":"17.52","prices":"39.80","title":"次第花开","zuozhe":"希阿荣博堪布","xiaoliang":"40508","kucun":"1178","chubanshe":"海南","chubanrqi":"2020-08-12"}
         ],
    "tushu":[
	  {"id":31,"lujin1":"首页","lujin2":"图书频道","imgurl":"img/wenxue1.jpg","imgurl2":"img/wenxuelun1.jpg","xiangqingtu":"img/wenxuetu1.jpg","price":"30.68","prices":"47.20","title":"西游记原著 上下共2册","zuozhe":"(明)吴承恩著","xiaoliang":"71547","kucun":"2284","chubanshe":"人民文学","chubanrqi":"2019-03-10"},
	  {"id":32,"lujin1":"首页","lujin2":"图书频道","imgurl":"img/wenxue3.jpg","imgurl2":"img/wenxuelun3.jpg","xiangqingtu":"img/wenxuetu3.jpg","price":"31.50","prices":"43.00","title":"哈利波特与魔法石魔幻小说","zuozhe":"(英)J.K.罗琳","xiaoliang":"15969","kucun":"767","chubanshe":"人民文学","chubanrqi":"2020-03-28"},
	  {"id":33,"lujin1":"首页","lujin2":"图书频道","imgurl":"img/wenxue5.jpg","imgurl2":"img/wenxuelun5.jpg","xiangqingtu":"img/wenxuetu5.jpg","price":"45.50","prices":"119.20","title":"四大名著全套小学生版4册","zuozhe":"刘敬余","xiaoliang":"27850","kucun":"2164","chubanshe":"北京教育","chubanrqi":"2018-04-12"},
	  {"id":34,"lujin1":"首页","lujin2":"图书频道","imgurl":"img/wenxue7.jpg","imgurl2":"img/wenxuelun7.jpg","xiangqingtu":"img/wenxuetu7.jpg","price":"188.00","prices":"980.00","title":"资治通鉴 （绸面精装16开.全六卷）","zuozhe":"司马光","xiaoliang":"1396","kucun":"196","chubanshe":"光明日报","chubanrqi":"2018-05-10"},
	  {"id":35,"lujin1":"首页","lujin2":"图书频道","imgurl":"img/wenxue9.jpg","imgurl2":"img/wenxuelun9.jpg","xiangqingtu":"img/wenxuetu9.jpg","price":"59.60","prices":"298.00","title":"鲁迅经典全集(共10册)","zuozhe":"鲁迅","xiaoliang":"20545","kucun":"887","chubanshe":"中国文史","chubanrqi":"2018-06-10"},
	  {"id":36,"lujin1":"首页","lujin2":"图书频道","imgurl":"img/wenxue11.jpg","imgurl2":"img/wenxuelun11.jpg","xiangqingtu":"img/wenxuetu11.jpg","price":"42.82","prices":"192.00","title":"浪漫古典行（全六册）","zuozhe":"蕴玉","xiaoliang":"1789","kucun":"128","chubanshe":"中国华侨","chubanrqi":"2018-03-17"},
	  {"id":37,"lujin1":"首页","lujin2":"图书频道","imgurl":"img/wenxue13.jpg","imgurl2":"img/wenxuelun13.jpg","xiangqingtu":"img/wenxuetu13.jpg","price":"13.76","prices":"25.00","title":"罗生门","zuozhe":"(日)芥川龙之介","xiaoliang":"43954","kucun":"288","chubanshe":"吉林出版集团","chubanrqi":"2019-02-18"},
	  {"id":38,"lujin1":"首页","lujin2":"图书频道","imgurl":"img/wenxue15.jpg","imgurl2":"img/wenxuelun15.jpg","xiangqingtu":"img/wenxuetu15.jpg","price":"17.50","prices":"36.00","title":"银河帝国1基地 七年级下","zuozhe":"(美)艾萨克·阿西莫夫","xiaoliang":"93048","kucun":"1634","chubanshe":"江苏文艺","chubanrqi":"2019-03-15"},
	  {"id":39,"lujin1":"首页","lujin2":"图书频道","imgurl":"img/wenxue17.jpg","imgurl2":"img/wenxuelun17.jpg","xiangqingtu":"img/wenxuetu17.jpg","price":"19.00","prices":"38.00","title":"流浪地球","zuozhe":"刘慈欣","xiaoliang":"6362","kucun":"1382","chubanshe":"中国华侨","chubanrqi":"2020-09-17"},
	  {"id":40,"lujin1":"首页","lujin2":"图书频道","imgurl":"img/wenxue19.jpg","imgurl2":"img/wenxuelun19.jpg","xiangqingtu":"img/wenxuetu19.jpg","price":"28.50","prices":"38.00","title":"苏菲的世界","zuozhe":"(挪威)乔斯坦·贾德","xiaoliang":"52810","kucun":"7315","chubanshe":"作家","chubanrqi":"2018-03-19"},
	  {"id":41,"lujin1":"首页","lujin2":"图书频道","imgurl":"img/wenxue21.jpg","imgurl2":"img/wenxuelun21.jpg","xiangqingtu":"img/wenxuetu21.jpg","price":"112.10","prices":"151.80","title":"杀破狼（共3册）","zuozhe":"PRIEST","xiaoliang":"5803","kucun":"279","chubanshe":"湖南文艺","chubanrqi":"2018-02-12"},
	  {"id":42,"lujin1":"首页","lujin2":"图书频道","imgurl":"img/wenxue23.jpg","imgurl2":"img/wenxuelun23.jpg","xiangqingtu":"img/wenxuetu23.jpg","price":"41.30","prices":"59.00","title":"文城 余华新书","zuozhe":"余华","xiaoliang":"37890","kucun":"5886","chubanshe":"北京十月文艺","chubanrqi":"2019-02-15"}
          ],
    "tongshu":[
	  {"id":43,"lujin1":"首页","lujin2":"童书频道","imgurl":"img/tongshu16.jpeg","imgurl2":"img/tongshulun16.jpeg","xiangqingtu":"img/tongshutu16.jpeg","price":"42.84","prices":"140.00","title":"曹文轩画本5册","zuozhe":"曹文轩","xiaoliang":"2788","kucun":"157","chubanshe":"长江少儿","chubanrqi":"2020-04-01"},
	  {"id":44,"lujin1":"首页","lujin2":"童书频道","imgurl":"img/tongshu20.jpeg","imgurl2":"img/tongshulun20.jpeg","xiangqingtu":"img/tongshutu20.jpeg","price":"41.05","prices":"94.80","title":"探索动物之旅--奇趣动物绘本6册","zuozhe":"陈琦","xiaoliang":"3743","kucun":"345","chubanshe":"山东教育","chubanrqi":"2018-11-12"},
	  {"id":45,"lujin1":"首页","lujin2":"童书频道","imgurl":"img/tongshu24.jpeg","imgurl2":"img/tongshulun24.jpeg","xiangqingtu":"img/tongshutu24.jpeg","price":"33.74","prices":"214.00","title":"国际大奖名著系列 全10册","zuozhe":"连东星","xiaoliang":"2315","kucun":"121","chubanshe":"世界图书出版公司","chubanrqi":"2020-03-19"},
	  {"id":46,"lujin1":"首页","lujin2":"童书频道","imgurl":"img/tongshu15.jpeg","imgurl2":"img/tongshulun15.jpeg","xiangqingtu":"img/tongshutu15.jpeg","price":"21.50","prices":"51.20","title":"中华优秀传统文化·成语故事（全4册）","zuozhe":"两两工作室","xiaoliang":"3404","kucun":"65","chubanshe":"哈尔滨","chubanrqi":"2019-06-01"},
	  {"id":47,"lujin1":"首页","lujin2":"童书频道","imgurl":"img/tongshu31.jpeg","imgurl2":"img/tongshulun31.jpeg","xiangqingtu":"img/tongshutu31.jpeg","price":"67.88","prices":"175.00","title":"彩虹桥动物母爱绘本(共5册)","zuozhe":"沈石溪","xiaoliang":"344","kucun":"183","chubanshe":"浙江教育","chubanrqi":"2020-10-23"},
	  {"id":48,"lujin1":"首页","lujin2":"童书频道","imgurl":"img/tongshu21.jpeg","imgurl2":"img/tongshulun21.jpeg","xiangqingtu":"img/tongshutu21.jpeg","price":"68.00","prices":"90.00","title":"汤小米上学记二年级","zuozhe":"刘香英","xiaoliang":"293","kucun":"651","chubanshe":"三辰影库音像","chubanrqi":"2020-12-01"},
	  {"id":49,"lujin1":"首页","lujin2":"童书频道","imgurl":"img/tongshu26.jpeg","imgurl2":"img/tongshulun26.jpeg","xiangqingtu":"img/tongshutu26.jpeg","price":"93.98","prices":"240.00","title":"宝宝情绪行为管理小画书 40册","zuozhe":"韩晶","xiaoliang":"37930","kucun":"1411","chubanshe":"江西教育","chubanrqi":"2018-06-09"},
	  {"id":50,"lujin1":"首页","lujin2":"童书频道","imgurl":"img/tongshu23.jpeg","imgurl2":"img/tongshulun23.jpeg","xiangqingtu":"img/tongshutu23.jpeg","price":"47.53","prices":"102.40","title":"童话山海经 注音版8册","zuozhe":"萧袤","xiaoliang":"5515","kucun":"285","chubanshe":"明天","chubanrqi":"2018-07-07"},
	  {"id":51,"lujin1":"首页","lujin2":"童书频道","imgurl":"img/tongshu25.jpeg","imgurl2":"img/tongshulun25.jpeg","xiangqingtu":"img/tongshutu25.jpeg","price":"51.35","prices":"158.00","title":"刘兴诗爷爷讲给孩子的中国地理","zuozhe":"刘兴诗","xiaoliang":"7036","kucun":"177","chubanshe":"长江少儿","chubanrqi":"2019-03-12"},
	  {"id":52,"lujin1":"首页","lujin2":"童书频道","imgurl":"img/tongshu23.jpeg","imgurl2":"img/tongshulun23.jpeg","xiangqingtu":"img/tongshutu23.jpeg","price":"47.53","prices":"102.40","title":"童话山海经 注音版8册","zuozhe":"萧袤","xiaoliang":"5515","kucun":"285","chubanshe":"明天","chubanrqi":"2018-07-07"},
	  {"id":53,"lujin1":"首页","lujin2":"童书频道","imgurl":"img/tongshu22.jpeg","imgurl2":"img/tongshulun22.jpeg","xiangqingtu":"img/tongshutu22.jpeg","price":"15.12","prices":"53.60","title":"中国神话故事(插图典藏本上下)","zuozhe":"周武广","xiaoliang":"887","kucun":"341","chubanshe":"沈阳","chubanrqi":"2019-05-01"},
	  {"id":54,"lujin1":"首页","lujin2":"童书频道","imgurl":"img/tongshu24.jpeg","imgurl2":"img/tongshulun24.jpeg","xiangqingtu":"img/tongshutu24.jpeg","price":"33.74","prices":"214.00","title":"国际大奖名著系列 全10册","zuozhe":"连东星","xiaoliang":"2315","kucun":"121","chubanshe":"世界图书出版公司","chubanrqi":"2020-03-19"}
          ],
    "yuanban":[
	  {"id":55,"lujin1":"首页","lujin2":"原版图书","imgurl":"img/renwen2.jpg","imgurl2":"img/renwenlun2.jpg","xiangqingtu":"img/renwentu2.jpg","price":"131.01","prices":"195.00","title":"精装读书会-历史旅行","zuozhe":"毛帅","xiaoliang":"173","kucun":"122","chubanshe":"四川人民","chubanrqi":"2021-01-01"},
	  {"id":56,"lujin1":"首页","lujin2":"原版图书","imgurl":"img/renwen4.jpg","imgurl2":"img/renwenlun4.jpg","xiangqingtu":"img/renwentu4.jpg","price":"36.00","prices":"179.00","title":"受益一生（全五册）","zuozhe":"李源","xiaoliang":"239","kucun":"128","chubanshe":"四川人民","chubanrqi":"2018-05-05"},
	  {"id":57,"lujin1":"首页","lujin2":"原版图书","imgurl":"img/renwen6.jpg","imgurl2":"img/renwenlun6.jpg","xiangqingtu":"img/renwentu6.jpg","price":"26.10","prices":"58.00","title":"极简中国史","zuozhe":"吕思勉","xiaoliang":"669","kucun":"126","chubanshe":"江苏文艺","chubanrqi":"2019-09-29"},
	  {"id":58,"lujin1":"首页","lujin2":"原版图书","imgurl":"img/renwen8.jpg","imgurl2":"img/renwenlun8.jpg","xiangqingtu":"img/renwentu8.jpg","price":"188.00","prices":"262.00","title":"历史绝对很有趣系列（全7册）","zuozhe":"李飞","xiaoliang":"767","kucun":"125","chubanshe":"天津人民","chubanrqi":"2020-07-07"},
	  {"id":59,"lujin1":"首页","lujin2":"原版图书","imgurl":"img/renwen10.jpg","imgurl2":"img/renwenlun10.jpg","xiangqingtu":"img/renwentu10.jpg","price":"24.90","prices":"49.80","title":"目光","zuozhe":"陶勇","xiaoliang":"8085","kucun":"414","chubanshe":"百花洲文艺","chubanrqi":"2019-08-18"},
	  {"id":60,"lujin1":"首页","lujin2":"原版图书","imgurl":"img/renwen12.jpg","imgurl2":"img/renwenlun12.jpg","xiangqingtu":"img/renwentu12.jpg","price":"14.36","prices":"32.00","title":"非暴力沟通(实践篇)","zuozhe":"(美)马歇尔·卢森堡","xiaoliang":"55874","kucun":"767","chubanshe":"江苏人民","chubanrqi":"2019-07-13"},
	  {"id":61,"lujin1":"首页","lujin2":"原版图书","imgurl":"img/renwen14.jpg","imgurl2":"img/renwenlun14.jpg","xiangqingtu":"img/renwentu14.jpg","price":"17.90","prices":"38.00","title":"文化苦旅(新版)","zuozhe":"余秋雨","xiaoliang":"52176","kucun":"1109","chubanshe":"长江文艺","chubanrqi":"2019-09-18"},
	  {"id":62,"lujin1":"首页","lujin2":"原版图书","imgurl":"img/renwen16.jpg","imgurl2":"img/renwenlun16.jpg","xiangqingtu":"img/renwentu16.jpg","price":"26.02","prices":"39.00","title":"刻意练习(如何从新手到大师)","zuozhe":"(美)安德斯·艾利克森","xiaoliang":"78556","kucun":"3289","chubanshe":"机械工业","chubanrqi":"2018-01-23"},
	  {"id":63,"lujin1":"首页","lujin2":"原版图书","imgurl":"img/renwen18.jpg","imgurl2":"img/renwenlun18.jpg","xiangqingtu":"img/renwentu18.jpg","price":"131.57","prices":"259.40","title":"半小时漫画中国史","zuozhe":"陈磊","xiaoliang":"1244","kucun":"1189","chubanshe":"文汇","chubanrqi":"2019-05-06"},
	  {"id":64,"lujin1":"首页","lujin2":"原版图书","imgurl":"img/renwen20.jpg","imgurl2":"img/renwenlun20.jpg","xiangqingtu":"img/renwentu20.jpg","price":"18.58","prices":"39.80","title":"乌合之众(群体心理研究)","zuozhe":"(法)古斯塔夫·勒庞","xiaoliang":"9734","kucun":"565","chubanshe":"中国友谊","chubanrqi":"2020-12-03"},
	  {"id":65,"lujin1":"首页","lujin2":"原版图书","imgurl":"img/renwen22.jpg","imgurl2":"img/renwenlun22.jpg","xiangqingtu":"img/renwentu22.jpg","price":"22.90","prices":"34.90","title":"趣说中国史","zuozhe":"趣哥","xiaoliang":"22626","kucun":"1523","chubanshe":"北京文艺","chubanrqi":"2020-12-21"},
	  {"id":66,"lujin1":"首页","lujin2":"原版图书","imgurl":"img/renwen24.jpg","imgurl2":"img/renwenlun24.jpg","xiangqingtu":"img/renwentu24.jpg","price":"23.44","prices":"49.90","title":"人间值得(精)","zuozhe":"(日)中村恒子","xiaoliang":"22755","kucun":"2348","chubanshe":"北京日报","chubanrqi":"2019-06-16"}
         ],
    "jingpin":[
	  {"id":67,"lujin1":"少儿图书","lujin2":"精品推荐","imgurl":"img/tongshu28.jpeg","imgurl2":"img/tongshulun28.jpeg","xiangqingtu":"img/tongshutu28.jpeg","price":"29.54","prices":"92.00","title":"中华上下五千年(共4册)","zuozhe":"木头人儿童创想中心","xiaoliang":"288845","kucun":"268","chubanshe":"煤炭工业","chubanrqi":"2020-11-17"},
	  {"id":68,"lujin1":"少儿图书","lujin2":"精品推荐","imgurl":"img/tongshu27.jpeg","imgurl2":"img/tongshulun27.jpeg","xiangqingtu":"img/tongshutu27.jpeg","price":"26.34","prices":"80.00","title":"中国孩子钟爱的十万个为什么（共8册）","zuozhe":"嘉良传媒","xiaoliang":"89385","kucun":"815","chubanshe":"海豚","chubanrqi":"2019-03-24"},
	  {"id":69,"lujin1":"少儿图书","lujin2":"精品推荐","imgurl":"img/tongshu29.jpeg","imgurl2":"img/tongshulun29.jpeg","xiangqingtu":"img/tongshutu29.jpeg","price":"13.76","prices":"19.80","title":"一年级大个子二年级小个子故事书","zuozhe":"(日)古田足日","xiaoliang":"147468","kucun":"1516","chubanshe":"接力","chubanrqi":"2019-09-25"},
	  {"id":70,"lujin1":"少儿图书","lujin2":"精品推荐","imgurl":"img/tongshu19.jpeg","imgurl2":"img/tongshulun19.jpeg","xiangqingtu":"img/tongshutu19.jpeg","price":"28.38","prices":"129.00","title":"宝宝的第一本洞洞认知书-动物等五册","zuozhe":"胡媛媛","xiaoliang":"7753","kucun":"357","chubanshe":"北方妇儿","chubanrqi":"2018-09-16"}
	     ],
	"bianji":[
	  {"id":71,"lujin1":"少儿图书","lujin2":"编辑推荐","imgurl":"img/tongshu16.jpeg","imgurl2":"img/tongshulun16.jpeg","xiangqingtu":"img/tongshutu16.jpeg","price":"42.84","prices":"140.00","title":"曹文轩画本5册","zuozhe":"曹文轩","xiaoliang":"2788","kucun":"157","chubanshe":"长江少儿","chubanrqi":"2020-04-01"},
	  {"id":72,"lujin1":"少儿图书","lujin2":"编辑推荐","imgurl":"img/tongshu20.jpeg","imgurl2":"img/tongshulun20.jpeg","xiangqingtu":"img/tongshutu20.jpeg","price":"41.05","prices":"94.80","title":"探索动物之旅--奇趣动物绘本6册","zuozhe":"陈琦","xiaoliang":"3743","kucun":"345","chubanshe":"山东教育","chubanrqi":"2018-11-12"},
	  {"id":73,"lujin1":"少儿图书","lujin2":"编辑推荐","imgurl":"img/tongshu24.jpeg","imgurl2":"img/tongshulun24.jpeg","xiangqingtu":"img/tongshutu24.jpeg","price":"33.74","prices":"214.00","title":"国际大奖名著系列 全10册","zuozhe":"连东星","xiaoliang":"2315","kucun":"121","chubanshe":"世界图书出版公司","chubanrqi":"2020-03-19"},
	  {"id":74,"lujin1":"少儿图书","lujin2":"编辑推荐","imgurl":"img/tongshu15.jpeg","imgurl2":"img/tongshulun15.jpeg","xiangqingtu":"img/tongshutu15.jpeg","price":"21.50","prices":"51.20","title":"中华优秀传统文化·成语故事（全4册）","zuozhe":"两两工作室","xiaoliang":"3404","kucun":"65","chubanshe":"哈尔滨","chubanrqi":"2019-06-01"},
	  {"id":75,"lujin1":"少儿图书","lujin2":"编辑推荐","imgurl":"img/tongshu31.jpeg","imgurl2":"img/tongshulun31.jpeg","xiangqingtu":"img/tongshutu31.jpeg","price":"67.88","prices":"175.00","title":"彩虹桥动物母爱绘本(共5册)","zuozhe":"沈石溪","xiaoliang":"344","kucun":"183","chubanshe":"浙江教育","chubanrqi":"2020-10-23"},
	  {"id":76,"lujin1":"少儿图书","lujin2":"编辑推荐","imgurl":"img/tongshu21.jpeg","imgurl2":"img/tongshulun21.jpeg","xiangqingtu":"img/tongshutu21.jpeg","price":"68.00","prices":"90.00","title":"汤小米上学记二年级","zuozhe":"刘香英","xiaoliang":"293","kucun":"651","chubanshe":"三辰影库音像","chubanrqi":"2020-12-01"},
	  {"id":77,"lujin1":"少儿图书","lujin2":"编辑推荐","imgurl":"img/tongshu26.jpeg","imgurl2":"img/tongshulun26.jpeg","xiangqingtu":"img/tongshutu26.jpeg","price":"93.98","prices":"240.00","title":"宝宝情绪行为管理小画书 40册","zuozhe":"韩晶","xiaoliang":"37930","kucun":"1411","chubanshe":"江西教育","chubanrqi":"2018-06-09"},
	  {"id":78,"lujin1":"少儿图书","lujin2":"编辑推荐","imgurl":"img/tongshu23.jpeg","imgurl2":"img/tongshulun23.jpeg","xiangqingtu":"img/tongshutu23.jpeg","price":"47.53","prices":"102.40","title":"童话山海经 注音版8册","zuozhe":"萧袤","xiaoliang":"5515","kucun":"285","chubanshe":"明天","chubanrqi":"2018-07-07"},
	  {"id":79,"lujin1":"少儿图书","lujin2":"编辑推荐","imgurl":"img/tongshu25.jpeg","imgurl2":"img/tongshulun25.jpeg","xiangqingtu":"img/tongshutu25.jpeg","price":"51.35","prices":"158.00","title":"刘兴诗爷爷讲给孩子的中国地理","zuozhe":"刘兴诗","xiaoliang":"7036","kucun":"177","chubanshe":"长江少儿","chubanrqi":"2019-03-12"},
	  {"id":80,"lujin1":"少儿图书","lujin2":"编辑推荐","imgurl":"img/tongshu23.jpeg","imgurl2":"img/tongshulun23.jpeg","xiangqingtu":"img/tongshutu23.jpeg","price":"47.53","prices":"102.40","title":"童话山海经 注音版8册","zuozhe":"萧袤","xiaoliang":"5515","kucun":"285","chubanshe":"明天","chubanrqi":"2018-07-07"},
	  {"id":81,"lujin1":"少儿图书","lujin2":"编辑推荐","imgurl":"img/tongshu22.jpeg","imgurl2":"img/tongshulun22.jpeg","xiangqingtu":"img/tongshutu22.jpeg","price":"15.12","prices":"53.60","title":"中国神话故事(插图典藏本上下)","zuozhe":"周武广","xiaoliang":"887","kucun":"341","chubanshe":"沈阳","chubanrqi":"2019-05-01"},
	  {"id":82,"lujin1":"少儿图书","lujin2":"编辑推荐","imgurl":"img/tongshu24.jpeg","imgurl2":"img/tongshulun24.jpeg","xiangqingtu":"img/tongshutu24.jpeg","price":"33.74","prices":"214.00","title":"国际大奖名著系列 全10册","zuozhe":"连东星","xiaoliang":"2315","kucun":"121","chubanshe":"世界图书出版公司","chubanrqi":"2020-03-19"}
         ], 
    "zbhs":[
	  {"id":83,"lujin1":"少儿图书","lujin2":"重磅好书","imgurl":"img/tongshu1.jpeg","imgurl2":"img/tongshu1.jpeg","xiangqingtu":"img/tongshutu1.jpeg","price":"90.03","prices":"138.00","title":"DK儿童百科全书(精)","zuozhe":"美国DK公司","xiaoliang":"10066","kucun":"1610","chubanshe":"中国大百科","chubanrqi":"2010-06-01"},
	  {"id":84,"lujin1":"少儿图书","lujin2":"重磅好书","imgurl":"img/tongshu2.jpeg","imgurl2":"img/tongshulun2.jpeg","xiangqingtu":"img/tongshutu2.jpeg","price":"27.86","prices":"39.80","title":"小狗钱钱","zuozhe":"博多·舍费尔","xiaoliang":"43234","kucun":"2136","chubanshe":"中信","chubanrqi":"2021-01-01"},
	  {"id":85,"lujin1":"少儿图书","lujin2":"重磅好书","imgurl":"img/tongshu3.jpeg","imgurl2":"img/tongshulun3.jpeg","xiangqingtu":"img/tongshutu3.jpeg","price":"77.50","prices":"155.00","title":"我们的身体(精)","zuozhe":"(法)帕斯卡尔·艾德兰","xiaoliang":"8247","kucun":"383","chubanshe":"未来","chubanrqi":"2016-03-01"},
	  {"id":86,"lujin1":"少儿图书","lujin2":"重磅好书","imgurl":"img/tongshu4.jpeg","imgurl2":"img/tongshu4.jpeg","xiangqingtu":"img/tongshu4.jpeg","price":"39.80","prices":"79.60","title":"我爸爸&我妈妈(新版共2册)","zuozhe":"英)安东尼·布朗","xiaoliang":"9660","kucun":"609","chubanshe":"河北教育","chubanrqi":"2014-06-12"},
	  {"id":87,"lujin1":"少儿图书","lujin2":"重磅好书","imgurl":"img/tongshu5.jpeg","imgurl2":"img/tongshulun5.jpeg","xiangqingtu":"img/tongshu5.jpeg","price":"100.67","prices":"219.00","title":"孩子读得懂的山海经(共3册)(精)","zuozhe":"贺维芳","xiaoliang":"5093","kucun":"654","chubanshe":"北京理工大学","chubanrqi":"2020-11-01"},
	  {"id":88,"lujin1":"少儿图书","lujin2":"重磅好书","imgurl":"img/tongshu6.jpeg","imgurl2":"img/tongshulun6.jpeg","xiangqingtu":"img/tongshutu6.jpeg","price":"16.42","prices":"79.90","title":"和爸妈游中国(精)","zuozhe":"黄宇","xiaoliang":"1701","kucun":"128","chubanshe":"明天","chubanrqi":"2019-05-22"},
	  {"id":89,"lujin1":"少儿图书","lujin2":"重磅好书","imgurl":"img/tongshu7.jpeg","imgurl2":"img/tongshulun7.jpeg","xiangqingtu":"img/tongshutu7.jpeg","price":"21.90","prices":"43.80","title":"猜猜我有多爱你 早教启蒙故事","zuozhe":"[英]安妮塔·婕朗","xiaoliang":"26700","kucun":"161","chubanshe":"明天","chubanrqi":"2020-01-01"},
	  {"id":90,"lujin1":"少儿图书","lujin2":"重磅好书","imgurl":"img/tongshu8.jpeg","imgurl2":"img/tongshulun8.jpeg","xiangqingtu":"img/tongshutu8.jpeg","price":"138.6.","prices":"198.00","title":"你好艺术(共13册)","zuozhe":"(日)结城昌子","xiaoliang":"431","kucun":"57","chubanshe":"中信","chubanrqi":"2020-03-03"},
	  {"id":91,"lujin1":"少儿图书","lujin2":"重磅好书","imgurl":"img/tongshu9.jpeg","imgurl2":"img/tongshulun9.jpeg","xiangqingtu":"img/tongshutu9.jpeg","price":"27.65","prices":"39.50","title":"窗边的小豆豆 中小学生课外阅读","zuozhe":"(日)黑柳彻子","xiaoliang":"46793","kucun":"832","chubanshe":"南海","chubanrqi":"2018-06-01"},
	  {"id":92,"lujin1":"少儿图书","lujin2":"重磅好书","imgurl":"img/tongshu10.jpeg","imgurl2":"img/tongshu10.jpeg","xiangqingtu":"img/tongshutu10.jpeg","price":"75.68","prices":"140.00","title":"屁屁侦探套装 第一辑","zuozhe":"(日)Troll","xiaoliang":"1753","kucun":"617","chubanshe":"HACHETTE","chubanrqi":"2020-07-05"},
	  {"id":93,"lujin1":"少儿图书","lujin2":"重磅好书","imgurl":"img/tongshu11.jpeg","imgurl2":"img/tongshulun11.jpeg","xiangqingtu":"img/tongshutu11.jpeg","price":"45.47","prices":"84.00","title":"故宫里的大怪兽（第六辑）","zuozhe":"常怡","xiaoliang":"3609","kucun":"711","chubanshe":"中国大百科","chubanrqi":"2019-04-01"},
	  {"id":94,"lujin1":"少儿图书","lujin2":"重磅好书","imgurl":"img/tongshu12.jpeg","imgurl2":"img/tongshulun12.jpeg","xiangqingtu":"img/tongshutu12.jpeg","price":"81.90","prices":"126.00","title":"宫西达也恐龙系列(共7册)","zuozhe":"(日)宫西达也","xiaoliang":"31244","kucun":"1715","chubanshe":"二十一世纪","chubanrqi":"2020-08-20"}
         ],
    "rexiao":[
	  {"id":95,"lujin1":"少儿图书","lujin2":"热销TOP30","imgurl":"img/tongshu13.jpeg","imgurl2":"img/tongshulun13.jpeg","xiangqingtu":"img/tongshutu13.jpeg","price":"26.27","prices":"37.00","title":"夏洛的网(新)","zuozhe":"[美]E·B·怀特","xiaoliang":"39541","kucun":"1720","chubanshe":"上海译文","chubanrqi":"2020-05-07"},
	  {"id":96,"lujin1":"少儿图书","lujin2":"热销TOP30","imgurl":"img/tongshu14.jpeg","imgurl2":"img/tongshulun14.jpeg","xiangqingtu":"img/tongshutu14.jpeg","price":"71.49","prices":"149.00","title":"少年读史记（共5册）","zuozhe":"张嘉骅","xiaoliang":"20","kucun":"156","chubanshe":"青岛","chubanrqi":"2020-08-23"},
	  {"id":97,"lujin1":"少儿图书","lujin2":"热销TOP30","imgurl":"img/tongshu15.jpeg","imgurl2":"img/tongshulun15.jpeg","xiangqingtu":"img/tongshutu15.jpeg","price":"21.50","prices":"51.20","title":"中华优秀传统文化·成语故事（全4册）","zuozhe":"两两工作室","xiaoliang":"3404","kucun":"65","chubanshe":"哈尔滨","chubanrqi":"2019-06-01"},
	  {"id":98,"lujin1":"少儿图书","lujin2":"热销TOP30","imgurl":"img/tongshu16.jpeg","imgurl2":"img/tongshulun16.jpeg","xiangqingtu":"img/tongshutu16.jpeg","price":"42.84","prices":"140.00","title":"曹文轩画本5册","zuozhe":"曹文轩","xiaoliang":"2788","kucun":"157","chubanshe":"长江少儿","chubanrqi":"2020-04-01"},
	  {"id":99,"lujin1":"少儿图书","lujin2":"热销TOP30","imgurl":"img/tongshu2.jpeg","imgurl2":"img/tongshulun2.jpeg","xiangqingtu":"img/tongshutu2.jpeg","price":"27.86","prices":"39.80","title":"小狗钱钱","zuozhe":"博多·舍费尔","xiaoliang":"43234","kucun":"2136","chubanshe":"中信","chubanrqi":"2021-01-01"},
	  {"id":100,"lujin1":"少儿图书","lujin2":"热销TOP30","imgurl":"img/tongshu17.jpeg","imgurl2":"img/tongshulun17.jpeg","xiangqingtu":"img/tongshutu17.jpeg","price":"35.50","prices":"100.00","title":"沈石溪《狼王梦》画本 共5册","zuozhe":"沈石溪","xiaoliang":"1087","kucun":"221","chubanshe":"长江少儿","chubanrqi":"2019-03-03"},
	  {"id":101,"lujin1":"少儿图书","lujin2":"热销TOP30","imgurl":"img/tongshu18.jpeg","imgurl2":"img/tongshulun18.jpeg","xiangqingtu":"img/tongshutu18.jpeg","price":"17.20","prices":"60.00","title":"跟着古诗去旅行（全四册）","zuozhe":"严欢","xiaoliang":"1049","kucun":"137","chubanshe":"三辰影库音像","chubanrqi":"2019-05-05"},
	  {"id":102,"lujin1":"少儿图书","lujin2":"热销TOP30","imgurl":"img/tongshu19.jpeg","imgurl2":"img/tongshulun19.jpeg","xiangqingtu":"img/tongshutu19.jpeg","price":"28.38","prices":"129.00","title":"宝宝的第一本洞洞认知书-动物等五册","zuozhe":"胡媛媛","xiaoliang":"7753","kucun":"357","chubanshe":"北方妇儿","chubanrqi":"2018-09-16"},
	  {"id":103,"lujin1":"少儿图书","lujin2":"热销TOP30","imgurl":"img/tongshu3.jpeg","imgurl2":"img/tongshulun3.jpeg","xiangqingtu":"img/tongshutu3.jpeg","price":"77.50","prices":"155.00","title":"我们的身体(精)","zuozhe":"(法)帕斯卡尔·艾德兰","xiaoliang":"8247","kucun":"383","chubanshe":"未来","chubanrqi":"2016-03-01"},
	  {"id":104,"lujin1":"少儿图书","lujin2":"热销TOP30","imgurl":"img/tongshu20.jpeg","imgurl2":"img/tongshulun20.jpeg","xiangqingtu":"img/tongshutu20.jpeg","price":"41.05","prices":"94.80","title":"探索动物之旅--奇趣动物绘本6册","zuozhe":"陈琦","xiaoliang":"3743","kucun":"345","chubanshe":"山东教育","chubanrqi":"2018-11-12"},
	  {"id":105,"lujin1":"少儿图书","lujin2":"热销TOP30","imgurl":"img/tongshu21.jpeg","imgurl2":"img/tongshulun21.jpeg","xiangqingtu":"img/tongshutu21.jpeg","price":"68.00","prices":"90.00","title":"汤小米上学记二年级","zuozhe":"刘香英","xiaoliang":"293","kucun":"651","chubanshe":"三辰影库音像","chubanrqi":"2020-12-01"},
	  {"id":106,"lujin1":"少儿图书","lujin2":"热销TOP30","imgurl":"img/tongshu22.jpeg","imgurl2":"img/tongshulun22.jpeg","xiangqingtu":"img/tongshutu22.jpeg","price":"15.12","prices":"53.60","title":"中国神话故事(插图典藏本上下)","zuozhe":"周武广","xiaoliang":"887","kucun":"341","chubanshe":"沈阳","chubanrqi":"2019-05-01"},
	  {"id":107,"lujin1":"少儿图书","lujin2":"热销TOP30","imgurl":"img/tongshu6.jpeg","imgurl2":"img/tongshulun6.jpeg","xiangqingtu":"img/tongshutu6.jpeg","price":"16.42","prices":"79.90","title":"和爸妈游中国(精)","zuozhe":"黄宇","xiaoliang":"1701","kucun":"128","chubanshe":"明天","chubanrqi":"2019-05-22"},
	  {"id":108,"lujin1":"少儿图书","lujin2":"热销TOP30","imgurl":"img/tongshu23.jpeg","imgurl2":"img/tongshulun23.jpeg","xiangqingtu":"img/tongshutu23.jpeg","price":"47.53","prices":"102.40","title":"童话山海经 注音版8册","zuozhe":"萧袤","xiaoliang":"5515","kucun":"285","chubanshe":"明天","chubanrqi":"2018-07-07"},
	  {"id":109,"lujin1":"少儿图书","lujin2":"热销TOP30","imgurl":"img/tongshu24.jpeg","imgurl2":"img/tongshulun24.jpeg","xiangqingtu":"img/tongshutu24.jpeg","price":"33.74","prices":"214.00","title":"国际大奖名著系列 全10册","zuozhe":"连东星","xiaoliang":"2315","kucun":"121","chubanshe":"世界图书出版公司","chubanrqi":"2020-03-19"},
	  {"id":110,"lujin1":"少儿图书","lujin2":"热销TOP30","imgurl":"img/tongshu25.jpeg","imgurl2":"img/tongshulun25.jpeg","xiangqingtu":"img/tongshutu25.jpeg","price":"51.35","prices":"158.00","title":"刘兴诗爷爷讲给孩子的中国地理","zuozhe":"刘兴诗","xiaoliang":"7036","kucun":"177","chubanshe":"长江少儿","chubanrqi":"2019-03-12"},
	  {"id":111,"lujin1":"少儿图书","lujin2":"热销TOP30","imgurl":"img/tongshu7.jpeg","imgurl2":"img/tongshulun7.jpeg","xiangqingtu":"img/tongshutu7.jpeg","price":"21.90","prices":"43.80","title":"猜猜我有多爱你 早教启蒙故事","zuozhe":"[英]安妮塔·婕朗","xiaoliang":"26700","kucun":"161","chubanshe":"明天","chubanrqi":"2020-01-01"},
	  {"id":112,"lujin1":"少儿图书","lujin2":"热销TOP30","imgurl":"img/tongshu26.jpeg","imgurl2":"img/tongshulun26.jpeg","xiangqingtu":"img/tongshutu26.jpeg","price":"93.98","prices":"240.00","title":"宝宝情绪行为管理小画书 40册","zuozhe":"韩晶","xiaoliang":"37930","kucun":"1411","chubanshe":"江西教育","chubanrqi":"2018-06-09"},
	  {"id":113,"lujin1":"少儿图书","lujin2":"热销TOP30","imgurl":"img/tongshu27.jpeg","imgurl2":"img/tongshulun27.jpeg","xiangqingtu":"img/tongshutu27.jpeg","price":"26.34","prices":"80.00","title":"中国孩子钟爱的十万个为什么（共8册）","zuozhe":"嘉良传媒","xiaoliang":"89385","kucun":"815","chubanshe":"海豚","chubanrqi":"2019-03-24"},
	  {"id":114,"lujin1":"少儿图书","lujin2":"热销TOP30","imgurl":"img/tongshu28.jpeg","imgurl2":"img/tongshulun28.jpeg","xiangqingtu":"img/tongshutu28.jpeg","price":"29.54","prices":"92.00","title":"中华上下五千年(共4册)","zuozhe":"木头人儿童创想中心","xiaoliang":"288845","kucun":"268","chubanshe":"煤炭工业","chubanrqi":"2020-11-17"},
	  {"id":115,"lujin1":"少儿图书","lujin2":"热销TOP30","imgurl":"img/tongshu29.jpeg","imgurl2":"img/tongshulun29.jpeg","xiangqingtu":"img/tongshutu29.jpeg","price":"13.76","prices":"19.80","title":"一年级大个子二年级小个子故事书","zuozhe":"(日)古田足日","xiaoliang":"147468","kucun":"1516","chubanshe":"接力","chubanrqi":"2019-09-25"},
	  {"id":116,"lujin1":"少儿图书","lujin2":"热销TOP30","imgurl":"img/tongshu8.jpeg","imgurl2":"img/tongshulun8.jpeg","xiangqingtu":"img/tongshutu8.jpeg","price":"138.6.","prices":"198.00","title":"你好艺术(共13册)","zuozhe":"(日)结城昌子","xiaoliang":"431","kucun":"57","chubanshe":"中信","chubanrqi":"2020-03-03"},
	  {"id":117,"lujin1":"少儿图书","lujin2":"热销TOP30","imgurl":"img/tongshu30.jpeg","imgurl2":"img/tongshulun30.jpeg","xiangqingtu":"img/tongshu30.jpeg","price":"20.74","prices":"38.00","title":"三毛流浪记全集注音版张乐平著","zuozhe":"张乐平","xiaoliang":"39477","kucun":"724","chubanshe":"少年儿童","chubanrqi":"2018-12-25"},
	  {"id":118,"lujin1":"少儿图书","lujin2":"热销TOP30","imgurl":"img/tongshu31.jpeg","imgurl2":"img/tongshulun31.jpeg","xiangqingtu":"img/tongshutu31.jpeg","price":"67.88","prices":"175.00","title":"彩虹桥动物母爱绘本(共5册)","zuozhe":"沈石溪","xiaoliang":"344","kucun":"183","chubanshe":"浙江教育","chubanrqi":"2020-10-23"},
	  {"id":119,"lujin1":"少儿图书","lujin2":"热销TOP30","imgurl":"img/tongshu9.jpeg","imgurl2":"img/tongshulun9.jpeg","xiangqingtu":"img/tongshutu9.jpeg","price":"27.65","prices":"39.50","title":"窗边的小豆豆 中小学生课外阅读","zuozhe":"(日)黑柳彻子","xiaoliang":"46793","kucun":"832","chubanshe":"南海","chubanrqi":"2018-06-01"},
	  {"id":120,"lujin1":"少儿图书","lujin2":"热销TOP30","imgurl":"img/tongshu10.jpeg","imgurl2":"img/tongshu10.jpeg","xiangqingtu":"img/tongshutu10.jpeg","price":"75.68","prices":"140.00","title":"屁屁侦探套装 第一辑","zuozhe":"(日)Troll","xiaoliang":"1753","kucun":"617","chubanshe":"HACHETTE","chubanrqi":"2020-07-05"},
	  {"id":121,"lujin1":"少儿图书","lujin2":"热销TOP30","imgurl":"img/tongshu11.jpeg","imgurl2":"img/tongshulun11.jpeg","xiangqingtu":"img/tongshutu11.jpeg","price":"45.47","prices":"84.00","title":"故宫里的大怪兽（第六辑）","zuozhe":"常怡","xiaoliang":"3609","kucun":"711","chubanshe":"中国大百科","chubanrqi":"2019-04-01"},
	  {"id":122,"lujin1":"少儿图书","lujin2":"热销TOP30","imgurl":"img/tongshu12.jpeg","imgurl2":"img/tongshulun12.jpeg","xiangqingtu":"img/tongshutu12.jpeg","price":"81.90","prices":"126.00","title":"宫西达也恐龙系列(共7册)","zuozhe":"(日)宫西达也","xiaoliang":"31244","kucun":"1715","chubanshe":"二十一世纪","chubanrqi":"2020-08-20"},
	  {"id":123,"lujin1":"少儿图书","lujin2":"热销TOP30","imgurl":"img/tongshu1.jpeg","imgurl2":"img/tongshu1.jpeg","xiangqingtu":"img/tongshutu1.jpeg","price":"90.03","prices":"138.00","title":"DK儿童百科全书(精)","zuozhe":"美国DK公司","xiaoliang":"10066","kucun":"1610","chubanshe":"中国大百科","chubanrqi":"2010-06-01"},
	  {"id":124,"lujin1":"少儿图书","lujin2":"热销TOP30","imgurl":"img/tongshu5.jpeg","imgurl2":"img/tongshulun5.jpeg","xiangqingtu":"img/tongshu5.jpeg","price":"100.67","prices":"219.00","title":"孩子读得懂的山海经(共3册)(精)","zuozhe":"贺维芳","xiaoliang":"5093","kucun":"654","chubanshe":"北京理工大学","chubanrqi":"2020-11-01"}
	    ],
    "jingpin3":[
	  {"id":125,"lujin1":"人文社科","lujin2":"精品推荐","imgurl":"img/renwen25.jpg","imgurl2":"img/renwenlun25.jpg","xiangqingtu":"img/renwentu25.jpg","price":"38.50","prices":"55.00","title":"起床后的黄金1小时","zuozhe":"[日] 池田千惠","xiaoliang":"3416","kucun":"1160","chubanshe":"北京日报","chubanrqi":"2018-09-12"},
	  {"id":126,"lujin1":"人文社科","lujin2":"精品推荐","imgurl":"img/renwen26.jpg","imgurl2":"img/renwenlun26.jpg","xiangqingtu":"img/renwentu26.jpg","price":"16.06","prices":"32.00","title":"断舍离","zuozhe":"(日)山下英子","xiaoliang":"79485","kucun":"566","chubanshe":"广西科技","chubanrqi":"2018-02-17"},
	  {"id":127,"lujin1":"人文社科","lujin2":"精品推荐","imgurl":"img/renwen27.jpg","imgurl2":"img/renwenlun27.jpg","xiangqingtu":"img/renwentu27.jpg","price":"45.54","prices":"69.00","title":"开启你的高维智慧","zuozhe":"刘丰","xiaoliang":"8300","kucun":"692","chubanshe":"中国青年","chubanrqi":"2019-08-26"},
	  {"id":128,"lujin1":"人文社科","lujin2":"精品推荐","imgurl":"img/renwen29.jpg","imgurl2":"img/renwenlun29.jpg","xiangqingtu":"img/renwentu29.jpg","price":"30.64","prices":"56.00","title":"把自己当回事儿","zuozhe":"杨天真","xiaoliang":"15982","kucun":"543","chubanshe":"北京联合","chubanrqi":"2019-11-08"}
	     ],
    "bianji3":[
	  {"id":129,"lujin1":"人文社科","lujin2":"编辑推荐","imgurl":"img/renwen1.jpg","imgurl2":"img/renwenlun1.jpg","xiangqingtu":"img/renwentu1.jpg","price":"32.46","prices":"58.00","title":"中华上下五千年 共3册","zuozhe":"林汉达","xiaoliang":"72731","kucun":"666","chubanshe":"少年儿童","chubanrqi":"2020-04-19"},
	  {"id":130,"lujin1":"人文社科","lujin2":"编辑推荐","imgurl":"img/renwen3.jpg","imgurl2":"img/renwenlun3.jpg","xiangqingtu":"img/renwentu3.jpg","price":"24.97","prices":"88.00","title":"人生课堂（全三册）","zuozhe":"张洋","xiaoliang":"675","kucun":"123","chubanshe":"明主与建设","chubanrqi":"2020-05-23"},
	  {"id":131,"lujin1":"人文社科","lujin2":"编辑推荐","imgurl":"img/renwen5.jpg","imgurl2":"img/renwenlun5.jpg","xiangqingtu":"img/renwentu5.jpg","price":"23.05","prices":"68.00","title":"彩图全解山海经","zuozhe":"(汉)刘向","xiaoliang":"1786","kucun":"141","chubanshe":"中国华侨","chubanrqi":"2019-12-06"},
	  {"id":132,"lujin1":"人文社科","lujin2":"编辑推荐","imgurl":"img/renwen7.jpg","imgurl2":"img/renwenlun7.jpg","xiangqingtu":"img/renwentu7.jpg","price":"32.30","prices":"58.00","title":"内在的星空","zuozhe":"余秋雨","xiaoliang":"575","kucun":"187","chubanshe":"北京联合","chubanrqi":"2018-01-23"},
	  {"id":133,"lujin1":"人文社科","lujin2":"编辑推荐","imgurl":"img/renwen9.jpg","imgurl2":"img/renwenlun9.jpg","xiangqingtu":"img/renwentu9.jpg","price":"21.39","prices":"42.00","title":"半小时漫画科学史","zuozhe":"陈磊","xiaoliang":"4064","kucun":"324","chubanshe":"文汇","chubanrqi":"2018-07-19"},
	  {"id":134,"lujin1":"人文社科","lujin2":"编辑推荐","imgurl":"img/renwen11.jpg","imgurl2":"img/renwenlun11.jpg","xiangqingtu":"img/renwentu11.jpg","price":"76.11","prices":"162.00","title":"民国才女传（套装共4册）","zuozhe":"清心","xiaoliang":"956","kucun":"159","chubanshe":"煤炭工业","chubanrqi":"2020-11-29"},
	  {"id":135,"lujin1":"人文社科","lujin2":"编辑推荐","imgurl":"img/renwen13.jpg","imgurl2":"img/renwenlun13.jpg","xiangqingtu":"img/renwentu13.jpg","price":"18.00","prices":"36.00","title":"亲爱的安德烈","zuozhe":"安德烈","xiaoliang":"159276","kucun":"1321","chubanshe":"广西师大","chubanrqi":"2020-01-21"},
	  {"id":136,"lujin1":"人文社科","lujin2":"编辑推荐","imgurl":"img/renwen15.jpg","imgurl2":"img/renwenlun15.jpg","xiangqingtu":"img/renwentu15.jpg","price":"18.67","prices":"32.00","title":"且以优雅过一生(杨绛传)","zuozhe":"桑妮","xiaoliang":"25860","kucun":"149","chubanshe":"湖南文艺","chubanrqi":"2018-05-12"},
	  {"id":137,"lujin1":"人文社科","lujin2":"编辑推荐","imgurl":"img/renwen17.jpg","imgurl2":"img/renwenlun17.jpg","xiangqingtu":"img/renwentu17.jpg","price":"27.71","prices":"49.90","title":"高效能人士的七个习惯（钻石版）","zuozhe":"（美）史蒂芬","xiaoliang":"67888","kucun":"1880","chubanshe":"中国青年出版社","chubanrqi":"2019-02-17"},
	  {"id":138,"lujin1":"人文社科","lujin2":"编辑推荐","imgurl":"img/renwen19.jpg","imgurl2":"img/renwenlun19.jpg","xiangqingtu":"img/renwentu19.jpg","price":"22.72","prices":"32.00","title":"钝感力","zuozhe":"(日)渡边淳一","xiaoliang":"25304","kucun":"2789","chubanshe":"青岛","chubanrqi":"2018-07-18"},
	  {"id":139,"lujin1":"人文社科","lujin2":"编辑推荐","imgurl":"img/renwen21.jpg","imgurl2":"img/renwenlun21.jpg","xiangqingtu":"img/renwentu21.jpg","price":"21.17","prices":"38.00","title":"蛤蟆先生去看心理医生","zuozhe":"(英)罗伯特·戴博德","xiaoliang":"65088","kucun":"5841","chubanshe":"天津人民","chubanrqi":"2019-07-09"},
	  {"id":140,"lujin1":"人文社科","lujin2":"编辑推荐","imgurl":"img/renwen23.jpg","imgurl2":"img/renwenlun23.jpg","xiangqingtu":"img/renwentu23.jpg","price":"17.52","prices":"39.80","title":"次第花开","zuozhe":"希阿荣博堪布","xiaoliang":"40508","kucun":"1178","chubanshe":"海南","chubanrqi":"2020-08-12"}
         ],
    "zbhs3":[
	  {"id":141,"lujin1":"人文社科","lujin2":"重磅好书","imgurl":"img/renwen2.jpg","imgurl2":"img/renwenlun2.jpg","xiangqingtu":"img/renwentu2.jpg","price":"131.01","prices":"195.00","title":"精装读书会-历史旅行","zuozhe":"毛帅","xiaoliang":"173","kucun":"122","chubanshe":"四川人民","chubanrqi":"2021-01-01"},
	  {"id":142,"lujin1":"人文社科","lujin2":"重磅好书","imgurl":"img/renwen4.jpg","imgurl2":"img/renwenlun4.jpg","xiangqingtu":"img/renwentu4.jpg","price":"36.00","prices":"179.00","title":"受益一生（全五册）","zuozhe":"李源","xiaoliang":"239","kucun":"128","chubanshe":"四川人民","chubanrqi":"2018-05-05"},
	  {"id":143,"lujin1":"人文社科","lujin2":"重磅好书","imgurl":"img/renwen6.jpg","imgurl2":"img/renwenlun6.jpg","xiangqingtu":"img/renwentu6.jpg","price":"26.10","prices":"58.00","title":"极简中国史","zuozhe":"吕思勉","xiaoliang":"669","kucun":"126","chubanshe":"江苏文艺","chubanrqi":"2019-09-29"},
	  {"id":144,"lujin1":"人文社科","lujin2":"重磅好书","imgurl":"img/renwen8.jpg","imgurl2":"img/renwenlun8.jpg","xiangqingtu":"img/renwentu8.jpg","price":"188.00","prices":"262.00","title":"历史绝对很有趣系列（全7册）","zuozhe":"李飞","xiaoliang":"767","kucun":"125","chubanshe":"天津人民","chubanrqi":"2020-07-07"},
	  {"id":145,"lujin1":"人文社科","lujin2":"重磅好书","imgurl":"img/renwen10.jpg","imgurl2":"img/renwenlun10.jpg","xiangqingtu":"img/renwentu10.jpg","price":"24.90","prices":"49.80","title":"目光","zuozhe":"陶勇","xiaoliang":"8085","kucun":"414","chubanshe":"百花洲文艺","chubanrqi":"2019-08-18"},
	  {"id":146,"lujin1":"人文社科","lujin2":"重磅好书","imgurl":"img/renwen12.jpg","imgurl2":"img/renwenlun12.jpg","xiangqingtu":"img/renwentu12.jpg","price":"14.36","prices":"32.00","title":"非暴力沟通(实践篇)","zuozhe":"(美)马歇尔·卢森堡","xiaoliang":"55874","kucun":"767","chubanshe":"江苏人民","chubanrqi":"2019-07-13"},
	  {"id":147,"lujin1":"人文社科","lujin2":"重磅好书","imgurl":"img/renwen14.jpg","imgurl2":"img/renwenlun14.jpg","xiangqingtu":"img/renwentu14.jpg","price":"17.90","prices":"38.00","title":"文化苦旅(新版)","zuozhe":"余秋雨","xiaoliang":"52176","kucun":"1109","chubanshe":"长江文艺","chubanrqi":"2019-09-18"},
	  {"id":148,"lujin1":"人文社科","lujin2":"重磅好书","imgurl":"img/renwen16.jpg","imgurl2":"img/renwenlun16.jpg","xiangqingtu":"img/renwentu16.jpg","price":"26.02","prices":"39.00","title":"刻意练习(如何从新手到大师)","zuozhe":"(美)安德斯·艾利克森","xiaoliang":"78556","kucun":"3289","chubanshe":"机械工业","chubanrqi":"2018-01-23"},
	  {"id":149,"lujin1":"人文社科","lujin2":"重磅好书","imgurl":"img/renwen18.jpg","imgurl2":"img/renwenlun18.jpg","xiangqingtu":"img/renwentu18.jpg","price":"131.57","prices":"259.40","title":"半小时漫画中国史","zuozhe":"陈磊","xiaoliang":"1244","kucun":"1189","chubanshe":"文汇","chubanrqi":"2019-05-06"},
	  {"id":150,"lujin1":"人文社科","lujin2":"重磅好书","imgurl":"img/renwen20.jpg","imgurl2":"img/renwenlun20.jpg","xiangqingtu":"img/renwentu20.jpg","price":"18.58","prices":"39.80","title":"乌合之众(群体心理研究)","zuozhe":"(法)古斯塔夫·勒庞","xiaoliang":"9734","kucun":"565","chubanshe":"中国友谊","chubanrqi":"2020-12-03"},
	  {"id":151,"lujin1":"人文社科","lujin2":"重磅好书","imgurl":"img/renwen22.jpg","imgurl2":"img/renwenlun22.jpg","xiangqingtu":"img/renwentu22.jpg","price":"22.90","prices":"34.90","title":"趣说中国史","zuozhe":"趣哥","xiaoliang":"22626","kucun":"1523","chubanshe":"北京文艺","chubanrqi":"2020-12-21"},
	  {"id":152,"lujin1":"人文社科","lujin2":"重磅好书","imgurl":"img/renwen24.jpg","imgurl2":"img/renwenlun24.jpg","xiangqingtu":"img/renwentu24.jpg","price":"23.44","prices":"49.90","title":"人间值得(精)","zuozhe":"(日)中村恒子","xiaoliang":"22755","kucun":"2348","chubanshe":"北京日报","chubanrqi":"2019-06-16"}
         ],
    "rexiao3":[
	  {"id":153,"lujin1":"人文社科","lujin2":"热销TOP30","imgurl":"img/renwen1.jpg","imgurl2":"img/renwenlun1.jpg","xiangqingtu":"img/renwentu1.jpg","price":"32.46","prices":"58.00","title":"中华上下五千年 共3册","zuozhe":"林汉达","xiaoliang":"72731","kucun":"666","chubanshe":"少年儿童","chubanrqi":"2020-04-19"},
	  {"id":154,"lujin1":"人文社科","lujin2":"热销TOP30","imgurl":"img/renwen2.jpg","imgurl2":"img/renwenlun2.jpg","xiangqingtu":"img/renwentu2.jpg","price":"131.01","prices":"195.00","title":"精装读书会-历史旅行","zuozhe":"毛帅","xiaoliang":"173","kucun":"122","chubanshe":"四川人民","chubanrqi":"2021-01-01"},
	  {"id":155,"lujin1":"人文社科","lujin2":"热销TOP30","imgurl":"img/renwen3.jpg","imgurl2":"img/renwenlun3.jpg","xiangqingtu":"img/renwentu3.jpg","price":"24.97","prices":"88.00","title":"人生课堂（全三册）","zuozhe":"张洋","xiaoliang":"675","kucun":"123","chubanshe":"明主与建设","chubanrqi":"2020-05-23"},
	  {"id":156,"lujin1":"人文社科","lujin2":"热销TOP30","imgurl":"img/renwen4.jpg","imgurl2":"img/renwenlun4.jpg","xiangqingtu":"img/renwentu4.jpg","price":"36.00","prices":"179.00","title":"受益一生（全五册）","zuozhe":"李源","xiaoliang":"239","kucun":"128","chubanshe":"四川人民","chubanrqi":"2018-05-05"},
	  {"id":157,"lujin1":"人文社科","lujin2":"热销TOP30","imgurl":"img/renwen5.jpg","imgurl2":"img/renwenlun5.jpg","xiangqingtu":"img/renwentu5.jpg","price":"23.05","prices":"68.00","title":"彩图全解山海经","zuozhe":"(汉)刘向","xiaoliang":"1786","kucun":"141","chubanshe":"中国华侨","chubanrqi":"2019-12-06"},
	  {"id":158,"lujin1":"人文社科","lujin2":"热销TOP30","imgurl":"img/renwen6.jpg","imgurl2":"img/renwenlun6.jpg","xiangqingtu":"img/renwentu6.jpg","price":"26.10","prices":"58.00","title":"极简中国史","zuozhe":"吕思勉","xiaoliang":"669","kucun":"126","chubanshe":"江苏文艺","chubanrqi":"2019-09-29"},
	  {"id":159,"lujin1":"人文社科","lujin2":"热销TOP30","imgurl":"img/renwen7.jpg","imgurl2":"img/renwenlun7.jpg","xiangqingtu":"img/renwentu7.jpg","price":"32.30","prices":"58.00","title":"内在的星空","zuozhe":"余秋雨","xiaoliang":"575","kucun":"187","chubanshe":"北京联合","chubanrqi":"2018-01-23"},
	  {"id":160,"lujin1":"人文社科","lujin2":"热销TOP30","imgurl":"img/renwen8.jpg","imgurl2":"img/renwenlun8.jpg","xiangqingtu":"img/renwentu8.jpg","price":"188.00","prices":"262.00","title":"历史绝对很有趣系列（全7册）","zuozhe":"李飞","xiaoliang":"767","kucun":"125","chubanshe":"天津人民","chubanrqi":"2020-07-07"},
	  {"id":161,"lujin1":"人文社科","lujin2":"热销TOP30","imgurl":"img/renwen9.jpg","imgurl2":"img/renwenlun9.jpg","xiangqingtu":"img/renwentu9.jpg","price":"21.39","prices":"42.00","title":"半小时漫画科学史","zuozhe":"陈磊","xiaoliang":"4064","kucun":"324","chubanshe":"文汇","chubanrqi":"2018-07-19"},
	  {"id":162,"lujin1":"人文社科","lujin2":"热销TOP30","imgurl":"img/renwen10.jpg","imgurl2":"img/renwenlun10.jpg","xiangqingtu":"img/renwentu10.jpg","price":"24.90","prices":"49.80","title":"目光","zuozhe":"陶勇","xiaoliang":"8085","kucun":"414","chubanshe":"百花洲文艺","chubanrqi":"2019-08-18"},
	  {"id":163,"lujin1":"人文社科","lujin2":"热销TOP30","imgurl":"img/renwen11.jpg","imgurl2":"img/renwenlun11.jpg","xiangqingtu":"img/renwentu11.jpg","price":"76.11","prices":"162.00","title":"民国才女传（套装共4册）","zuozhe":"清心","xiaoliang":"956","kucun":"159","chubanshe":"煤炭工业","chubanrqi":"2020-11-29"},
	  {"id":164,"lujin1":"人文社科","lujin2":"热销TOP30","imgurl":"img/renwen12.jpg","imgurl2":"img/renwenlun12.jpg","xiangqingtu":"img/renwentu12.jpg","price":"14.36","prices":"32.00","title":"非暴力沟通(实践篇)","zuozhe":"(美)马歇尔·卢森堡","xiaoliang":"55874","kucun":"767","chubanshe":"江苏人民","chubanrqi":"2019-07-13"},
	  {"id":165,"lujin1":"人文社科","lujin2":"热销TOP30","imgurl":"img/renwen13.jpg","imgurl2":"img/renwenlun13.jpg","xiangqingtu":"img/renwentu13.jpg","price":"18.00","prices":"36.00","title":"亲爱的安德烈","zuozhe":"安德烈","xiaoliang":"159276","kucun":"1321","chubanshe":"广西师大","chubanrqi":"2020-01-21"},
	  {"id":166,"lujin1":"人文社科","lujin2":"热销TOP30","imgurl":"img/renwen14.jpg","imgurl2":"img/renwenlun14.jpg","xiangqingtu":"img/renwentu14.jpg","price":"17.90","prices":"38.00","title":"文化苦旅(新版)","zuozhe":"余秋雨","xiaoliang":"52176","kucun":"1109","chubanshe":"长江文艺","chubanrqi":"2019-09-18"},
	  {"id":167,"lujin1":"人文社科","lujin2":"热销TOP30","imgurl":"img/renwen15.jpg","imgurl2":"img/renwenlun15.jpg","xiangqingtu":"img/renwentu15.jpg","price":"18.67","prices":"32.00","title":"且以优雅过一生(杨绛传)","zuozhe":"桑妮","xiaoliang":"25860","kucun":"149","chubanshe":"湖南文艺","chubanrqi":"2018-05-12"},
	  {"id":168,"lujin1":"人文社科","lujin2":"热销TOP30","imgurl":"img/renwen16.jpg","imgurl2":"img/renwenlun16.jpg","xiangqingtu":"img/renwentu16.jpg","price":"26.02","prices":"39.00","title":"刻意练习(如何从新手到大师)","zuozhe":"(美)安德斯·艾利克森","xiaoliang":"78556","kucun":"3289","chubanshe":"机械工业","chubanrqi":"2018-01-23"},
	  {"id":169,"lujin1":"人文社科","lujin2":"热销TOP30","imgurl":"img/renwen17.jpg","imgurl2":"img/renwenlun17.jpg","xiangqingtu":"img/renwentu17.jpg","price":"27.71","prices":"49.90","title":"高效能人士的七个习惯（钻石版）","zuozhe":"（美）史蒂芬","xiaoliang":"67888","kucun":"1880","chubanshe":"中国青年出版社","chubanrqi":"2019-02-17"},
	  {"id":170,"lujin1":"人文社科","lujin2":"热销TOP30","imgurl":"img/renwen18.jpg","imgurl2":"img/renwenlun18.jpg","xiangqingtu":"img/renwentu18.jpg","price":"131.57","prices":"259.40","title":"半小时漫画中国史","zuozhe":"陈磊","xiaoliang":"1244","kucun":"1189","chubanshe":"文汇","chubanrqi":"2019-05-06"},
	  {"id":171,"lujin1":"人文社科","lujin2":"热销TOP30","imgurl":"img/renwen19.jpg","imgurl2":"img/renwenlun19.jpg","xiangqingtu":"img/renwentu19.jpg","price":"22.72","prices":"32.00","title":"钝感力","zuozhe":"(日)渡边淳一","xiaoliang":"25304","kucun":"2789","chubanshe":"青岛","chubanrqi":"2018-07-18"},
	  {"id":172,"lujin1":"人文社科","lujin2":"热销TOP30","imgurl":"img/renwen20.jpg","imgurl2":"img/renwenlun20.jpg","xiangqingtu":"img/renwentu20.jpg","price":"18.58","prices":"39.80","title":"乌合之众(群体心理研究)","zuozhe":"(法)古斯塔夫·勒庞","xiaoliang":"9734","kucun":"565","chubanshe":"中国友谊","chubanrqi":"2020-12-03"},
	  {"id":173,"lujin1":"人文社科","lujin2":"热销TOP30","imgurl":"img/renwen21.jpg","imgurl2":"img/renwenlun21.jpg","xiangqingtu":"img/renwentu21.jpg","price":"21.17","prices":"38.00","title":"蛤蟆先生去看心理医生","zuozhe":"(英)罗伯特·戴博德","xiaoliang":"65088","kucun":"5841","chubanshe":"天津人民","chubanrqi":"2019-07-09"},
	  {"id":174,"lujin1":"人文社科","lujin2":"热销TOP30","imgurl":"img/renwen22.jpg","imgurl2":"img/renwenlun22.jpg","xiangqingtu":"img/renwentu22.jpg","price":"22.90","prices":"34.90","title":"趣说中国史","zuozhe":"趣哥","xiaoliang":"22626","kucun":"1523","chubanshe":"北京文艺","chubanrqi":"2020-12-21"},
	  {"id":175,"lujin1":"人文社科","lujin2":"热销TOP30","imgurl":"img/renwen23.jpg","imgurl2":"img/renwenlun23.jpg","xiangqingtu":"img/renwentu23.jpg","price":"17.52","prices":"39.80","title":"次第花开","zuozhe":"希阿荣博堪布","xiaoliang":"40508","kucun":"1178","chubanshe":"海南","chubanrqi":"2020-08-12"},
	  {"id":176,"lujin1":"人文社科","lujin2":"热销TOP30","imgurl":"img/renwen24.jpg","imgurl2":"img/renwenlun24.jpg","xiangqingtu":"img/renwentu24.jpg","price":"23.44","prices":"49.90","title":"人间值得(精)","zuozhe":"(日)中村恒子","xiaoliang":"22755","kucun":"2348","chubanshe":"北京日报","chubanrqi":"2019-06-16"},
	  {"id":177,"lujin1":"人文社科","lujin2":"热销TOP30","imgurl":"img/renwen25.jpg","imgurl2":"img/renwenlun25.jpg","xiangqingtu":"img/renwentu25.jpg","price":"38.50","prices":"55.00","title":"起床后的黄金1小时","zuozhe":"[日] 池田千惠","xiaoliang":"3416","kucun":"1160","chubanshe":"北京日报","chubanrqi":"2018-09-12"},
	  {"id":178,"lujin1":"人文社科","lujin2":"热销TOP30","imgurl":"img/renwen26.jpg","imgurl2":"img/renwenlun26.jpg","xiangqingtu":"img/renwentu26.jpg","price":"16.06","prices":"32.00","title":"断舍离","zuozhe":"(日)山下英子","xiaoliang":"79485","kucun":"566","chubanshe":"广西科技","chubanrqi":"2018-02-17"},
	  {"id":179,"lujin1":"人文社科","lujin2":"热销TOP30","imgurl":"img/renwen27.jpg","imgurl2":"img/renwenlun27.jpg","xiangqingtu":"img/renwentu27.jpg","price":"45.54","prices":"69.00","title":"开启你的高维智慧","zuozhe":"刘丰","xiaoliang":"8300","kucun":"692","chubanshe":"中国青年","chubanrqi":"2019-08-26"},
	  {"id":180,"lujin1":"人文社科","lujin2":"热销TOP30","imgurl":"img/renwen28.jpg","imgurl2":"img/renwenlun28.jpg","xiangqingtu":"img/renwentu28.jpg","price":"10.26","prices":"38.00","title":"最强大脑","zuozhe":"鸿雁","xiaoliang":"4864","kucun":"456","chubanshe":"吉林文史","chubanrqi":"2020-09-13"},
	  {"id":181,"lujin1":"人文社科","lujin2":"热销TOP30","imgurl":"img/renwen29.jpg","imgurl2":"img/renwenlun29.jpg","xiangqingtu":"img/renwentu29.jpg","price":"30.64","prices":"56.00","title":"把自己当回事儿","zuozhe":"杨天真","xiaoliang":"15982","kucun":"543","chubanshe":"北京联合","chubanrqi":"2019-11-08"},
	  {"id":182,"lujin1":"人文社科","lujin2":"热销TOP30","imgurl":"img/renwen30.jpg","imgurl2":"img/renwenlun30.jpg","xiangqingtu":"img/renwentu30.jpg","price":"10.26","prices":"38.00","title":"超级记忆术","zuozhe":"鸿雁","xiaoliang":"36135","kucun":"608","chubanshe":"吉林文史","chubanrqi":"2018-05-28"}
	    ],
    "jingpin4":[
	  {"id":183,"lujin1":"文学艺术","lujin2":"精品推荐","imgurl":"img/wenxue25.jpg","imgurl2":"img/wenxuelun25.jpg","xiangqingtu":"img/wenxuetu25.jpg","price":"29.40","prices":"49.00","title":"心安即是归处","zuozhe":"季羡林","xiaoliang":"767","kucun":"320","chubanshe":"古吴轩","chubanrqi":"2018-02-15"},
	  {"id":184,"lujin1":"文学艺术","lujin2":"精品推荐","imgurl":"img/wenxue26.jpg","imgurl2":"img/wenxuelun26.jpg","xiangqingtu":"img/wenxuetu26.jpg","price":"46.68","prices":"93.00","title":"三体（1-3 共3册）","zuozhe":"刘慈欣","xiaoliang":"455304","kucun":"2724","chubanshe":"重庆","chubanrqi":"2019-11-23"},
	  {"id":185,"lujin1":"文学艺术","lujin2":"精品推荐","imgurl":"img/wenxue27.jpg","imgurl2":"img/wenxuelun27.jpg","xiangqingtu":"img/wenxuetu27.jpg","price":"24.50","prices":"35.00","title":"活着","zuozhe":"余华","xiaoliang":"60149","kucun":"4494","chubanshe":"北京文艺","chubanrqi":"2020-11-14"},
	  {"id":186,"lujin1":"文学艺术","lujin2":"精品推荐","imgurl":"img/wenxue28.jpg","imgurl2":"img/wenxuelun28.jpg","xiangqingtu":"img/wenxuetu28.jpg","price":"48.33","prices":"69.00","title":"霍乱时期的爱情","zuozhe":"马尔克斯","xiaoliang":"19564","kucun":"1867","chubanshe":"南海","chubanrqi":"2018-02-07"}
	    ],
    "bianji4":[
	  {"id":187,"lujin1":"文学艺术","lujin2":"编辑推荐","imgurl":"img/wenxue1.jpg","imgurl2":"img/wenxuelun1.jpg","xiangqingtu":"img/wenxuetu1.jpg","price":"30.68","prices":"47.20","title":"西游记原著 上下共2册","zuozhe":"(明)吴承恩著","xiaoliang":"71547","kucun":"2284","chubanshe":"人民文学","chubanrqi":"2019-03-10"},
	  {"id":188,"lujin1":"文学艺术","lujin2":"编辑推荐","imgurl":"img/wenxue3.jpg","imgurl2":"img/wenxuelun3.jpg","xiangqingtu":"img/wenxuetu3.jpg","price":"31.50","prices":"43.00","title":"哈利波特与魔法石魔幻小说","zuozhe":"(英)J.K.罗琳","xiaoliang":"15969","kucun":"767","chubanshe":"人民文学","chubanrqi":"2020-03-28"},
	  {"id":189,"lujin1":"文学艺术","lujin2":"编辑推荐","imgurl":"img/wenxue5.jpg","imgurl2":"img/wenxuelun5.jpg","xiangqingtu":"img/wenxuetu5.jpg","price":"45.50","prices":"119.20","title":"四大名著全套小学生版4册","zuozhe":"刘敬余","xiaoliang":"27850","kucun":"2164","chubanshe":"北京教育","chubanrqi":"2018-04-12"},
	  {"id":190,"lujin1":"文学艺术","lujin2":"编辑推荐","imgurl":"img/wenxue7.jpg","imgurl2":"img/wenxuelun7.jpg","xiangqingtu":"img/wenxuetu7.jpg","price":"188.00","prices":"980.00","title":"资治通鉴 （绸面精装16开.全六卷）","zuozhe":"司马光","xiaoliang":"1396","kucun":"196","chubanshe":"光明日报","chubanrqi":"2018-05-10"},
	  {"id":191,"lujin1":"文学艺术","lujin2":"编辑推荐","imgurl":"img/wenxue9.jpg","imgurl2":"img/wenxuelun9.jpg","xiangqingtu":"img/wenxuetu9.jpg","price":"59.60","prices":"298.00","title":"鲁迅经典全集(共10册)","zuozhe":"鲁迅","xiaoliang":"20545","kucun":"887","chubanshe":"中国文史","chubanrqi":"2018-06-10"},
	  {"id":192,"lujin1":"文学艺术","lujin2":"编辑推荐","imgurl":"img/wenxue11.jpg","imgurl2":"img/wenxuelun11.jpg","xiangqingtu":"img/wenxuetu11.jpg","price":"42.82","prices":"192.00","title":"浪漫古典行（全六册）","zuozhe":"蕴玉","xiaoliang":"1789","kucun":"128","chubanshe":"中国华侨","chubanrqi":"2018-03-17"},
	  {"id":193,"lujin1":"文学艺术","lujin2":"编辑推荐","imgurl":"img/wenxue13.jpg","imgurl2":"img/wenxuelun13.jpg","xiangqingtu":"img/wenxuetu13.jpg","price":"13.76","prices":"25.00","title":"罗生门","zuozhe":"(日)芥川龙之介","xiaoliang":"43954","kucun":"288","chubanshe":"吉林出版集团","chubanrqi":"2019-02-18"},
	  {"id":194,"lujin1":"文学艺术","lujin2":"编辑推荐","imgurl":"img/wenxue15.jpg","imgurl2":"img/wenxuelun15.jpg","xiangqingtu":"img/wenxuetu15.jpg","price":"17.50","prices":"36.00","title":"银河帝国1基地 七年级下","zuozhe":"(美)艾萨克·阿西莫夫","xiaoliang":"93048","kucun":"1634","chubanshe":"江苏文艺","chubanrqi":"2019-03-15"},
	  {"id":195,"lujin1":"文学艺术","lujin2":"编辑推荐","imgurl":"img/wenxue17.jpg","imgurl2":"img/wenxuelun17.jpg","xiangqingtu":"img/wenxuetu17.jpg","price":"19.00","prices":"38.00","title":"流浪地球","zuozhe":"刘慈欣","xiaoliang":"6362","kucun":"1382","chubanshe":"中国华侨","chubanrqi":"2020-09-17"},
	  {"id":196,"lujin1":"文学艺术","lujin2":"编辑推荐","imgurl":"img/wenxue19.jpg","imgurl2":"img/wenxuelun19.jpg","xiangqingtu":"img/wenxuetu19.jpg","price":"28.50","prices":"38.00","title":"苏菲的世界","zuozhe":"(挪威)乔斯坦·贾德","xiaoliang":"52810","kucun":"7315","chubanshe":"作家","chubanrqi":"2018-03-19"},
	  {"id":197,"lujin1":"文学艺术","lujin2":"编辑推荐","imgurl":"img/wenxue21.jpg","imgurl2":"img/wenxuelun21.jpg","xiangqingtu":"img/wenxuetu21.jpg","price":"112.10","prices":"151.80","title":"杀破狼（共3册）","zuozhe":"PRIEST","xiaoliang":"5803","kucun":"279","chubanshe":"湖南文艺","chubanrqi":"2018-02-12"},
	  {"id":198,"lujin1":"文学艺术","lujin2":"编辑推荐","imgurl":"img/wenxue23.jpg","imgurl2":"img/wenxuelun23.jpg","xiangqingtu":"img/wenxuetu23.jpg","price":"41.30","prices":"59.00","title":"文城 余华新书","zuozhe":"余华","xiaoliang":"37890","kucun":"5886","chubanshe":"北京十月文艺","chubanrqi":"2019-02-15"}
         ],
    "zbhs4":[
	  {"id":199,"lujin1":"文学艺术","lujin2":"重磅好书","imgurl":"img/wenxue2.jpg","imgurl2":"img/wenxuelun2.jpg","xiangqingtu":"img/wenxuetu2.jpg","price":"45.93","prices":"126.40","title":"冰心儿童文学全集共8册","zuozhe":"刘敬余","xiaoliang":"6513","kucun":"267","chubanshe":"北京教育","chubanrqi":"2020-03-10"},
	  {"id":200,"lujin1":"文学艺术","lujin2":"重磅好书","imgurl":"img/wenxue4.jpg","imgurl2":"img/wenxuelun4.jpg","xiangqingtu":"img/wenxuetu4.jpg","price":"50.90","prices":"99.80","title":"夜航船(上下)","zuozhe":"(明)张岱","xiaoliang":"3924","kucun":"690","chubanshe":"浙江文艺","chubanrqi":"2019-02-09"},
	  {"id":201,"lujin1":"文学艺术","lujin2":"重磅好书","imgurl":"img/wenxue6.jpg","imgurl2":"img/wenxuelun6.jpg","xiangqingtu":"img/wenxuetu6.jpg","price":"148.00","prices":"298.00","title":"老舍作品集（全八册 附书签）","zuozhe":"老舍","xiaoliang":"5875","kucun":"195","chubanshe":"北京联合","chubanrqi":"2020-08-16"},
	  {"id":202,"lujin1":"文学艺术","lujin2":"重磅好书","imgurl":"img/wenxue8.jpg","imgurl2":"img/wenxuelun8.jpg","xiangqingtu":"img/wenxuetu8.jpg","price":"29.90","prices":"59.80","title":"偏偏宠爱","zuozhe":"藤萝为枝","xiaoliang":"18346","kucun":"796","chubanshe":"青岛","chubanrqi":"2019-06-09"},
	  {"id":203,"lujin1":"文学艺术","lujin2":"重磅好书","imgurl":"img/wenxue10.jpg","imgurl2":"img/wenxuelun10.jpg","xiangqingtu":"img/wenxuetu10.jpg","price":"119.00","prices":"328.00","title":"鲁迅作品（全10册）","zuozhe":"鲁迅","xiaoliang":"1391","kucun":"139","chubanshe":"民主与建设","chubanrqi":"2020-07-14"},
	  {"id":204,"lujin1":"文学艺术","lujin2":"重磅好书","imgurl":"img/wenxue12.jpg","imgurl2":"img/wenxuelun12.jpg","xiangqingtu":"img/wenxuetu12.jpg","price":"50.75","prices":"72.00","title":"长征 上下2册","zuozhe":"王树增","xiaoliang":"4907","kucun":"384","chubanshe":"人民文学","chubanrqi":"2020-09-21"},
	  {"id":205,"lujin1":"文学艺术","lujin2":"重磅好书","imgurl":"img/wenxue14.jpg","imgurl2":"img/wenxuelun14.jpg","xiangqingtu":"img/wenxuetu14.jpg","price":"32.89","prices":"50.60","title":"水浒传原著 上下共2册","zuozhe":"施耐庵","xiaoliang":"52655","kucun":"1858","chubanshe":"人民文学","chubanrqi":"2018-06-24"},
	  {"id":206,"lujin1":"文学艺术","lujin2":"重磅好书","imgurl":"img/wenxue16.jpg","imgurl2":"img/wenxuelun16.jpg","xiangqingtu":"img/wenxuetu16.jpg","price":"26.00","prices":"40.00","title":"俗世奇人(共2册)","zuozhe":"冯骥才","xiaoliang":"30769","kucun":"1985","chubanshe":"浙江文学","chubanrqi":"2019-04-12"},
	  {"id":207,"lujin1":"文学艺术","lujin2":"重磅好书","imgurl":"img/wenxue18.jpg","imgurl2":"img/wenxuelun18.jpg","xiangqingtu":"img/wenxuetu18.jpg","price":"29.80","prices":"39.80","title":"平凡的世界 八年级","zuozhe":"路遥","xiaoliang":"58649","kucun":"679","chubanshe":"北京十月文艺","chubanrqi":"2019-03-18"},
	  {"id":208,"lujin1":"文学艺术","lujin2":"重磅好书","imgurl":"img/wenxue20.jpg","imgurl2":"img/wenxuelun20.jpg","xiangqingtu":"img/wenxuetu20.jpg","price":"21.87","prices":"36.00","title":"七年级阅读 红岩","zuozhe":"罗广斌","xiaoliang":"132714","kucun":"8712","chubanshe":"中国青年","chubanrqi":"2019-12-12"},
	  {"id":209,"lujin1":"文学艺术","lujin2":"重磅好书","imgurl":"img/wenxue22.jpg","imgurl2":"img/wenxuelun22.jpg","xiangqingtu":"img/wenxuetu22.jpg","price":"38.50","prices":"55.00","title":"人生海海","zuozhe":"麦家","xiaoliang":"13879","kucun":"1168","chubanshe":"北京十月文艺","chubanrqi":"2020-04-21"},
	  {"id":210,"lujin1":"文学艺术","lujin2":"重磅好书","imgurl":"img/wenxue24.jpg","imgurl2":"img/wenxuelun24.jpg","xiangqingtu":"img/wenxuetu24.jpg","price":"41.31","prices":"59.00","title":"你当像鸟飞往你的山","zuozhe":"塔拉·韦斯特弗","xiaoliang":"57279","kucun":"7189","chubanshe":"南海","chubanrqi":"2020-09-12"}
         ],
    "rexiao4":[
	  {"id":211,"lujin1":"文学艺术","lujin2":"热销TOP30","imgurl":"img/wenxue1.jpg","imgurl2":"img/wenxuelun1.jpg","xiangqingtu":"img/wenxuetu1.jpg","price":"30.68","prices":"47.20","title":"西游记原著 上下共2册","zuozhe":"(明)吴承恩著","xiaoliang":"71547","kucun":"2284","chubanshe":"人民文学","chubanrqi":"2019-03-10"},
	  {"id":212,"lujin1":"文学艺术","lujin2":"热销TOP30","imgurl":"img/wenxue2.jpg","imgurl2":"img/wenxuelun2.jpg","xiangqingtu":"img/wenxuetu2.jpg","price":"45.93","prices":"126.40","title":"冰心儿童文学全集共8册","zuozhe":"刘敬余","xiaoliang":"6513","kucun":"267","chubanshe":"北京教育","chubanrqi":"2020-03-10"},
	  {"id":213,"lujin1":"文学艺术","lujin2":"热销TOP30","imgurl":"img/wenxue3.jpg","imgurl2":"img/wenxuelun3.jpg","xiangqingtu":"img/wenxuetu3.jpg","price":"31.50","prices":"43.00","title":"哈利波特与魔法石魔幻小说","zuozhe":"(英)J.K.罗琳","xiaoliang":"15969","kucun":"767","chubanshe":"人民文学","chubanrqi":"2020-03-28"},
	  {"id":214,"lujin1":"文学艺术","lujin2":"热销TOP30","imgurl":"img/wenxue4.jpg","imgurl2":"img/wenxuelun4.jpg","xiangqingtu":"img/wenxuetu4.jpg","price":"50.90","prices":"99.80","title":"夜航船(上下)","zuozhe":"(明)张岱","xiaoliang":"3924","kucun":"690","chubanshe":"浙江文艺","chubanrqi":"2019-02-09"},
	  {"id":215,"lujin1":"文学艺术","lujin2":"热销TOP30","imgurl":"img/wenxue5.jpg","imgurl2":"img/wenxuelun5.jpg","xiangqingtu":"img/wenxuetu5.jpg","price":"45.50","prices":"119.20","title":"四大名著全套小学生版4册","zuozhe":"刘敬余","xiaoliang":"27850","kucun":"2164","chubanshe":"北京教育","chubanrqi":"2018-04-12"},
	  {"id":216,"lujin1":"文学艺术","lujin2":"热销TOP30","imgurl":"img/wenxue6.jpg","imgurl2":"img/wenxuelun6.jpg","xiangqingtu":"img/wenxuetu6.jpg","price":"148.00","prices":"298.00","title":"老舍作品集（全八册 附书签）","zuozhe":"老舍","xiaoliang":"5875","kucun":"195","chubanshe":"北京联合","chubanrqi":"2020-08-16"},
	  {"id":217,"lujin1":"文学艺术","lujin2":"热销TOP30","imgurl":"img/wenxue7.jpg","imgurl2":"img/wenxuelun7.jpg","xiangqingtu":"img/wenxuetu7.jpg","price":"188.00","prices":"980.00","title":"资治通鉴 （绸面精装16开.全六卷）","zuozhe":"司马光","xiaoliang":"1396","kucun":"196","chubanshe":"光明日报","chubanrqi":"2018-05-10"},
	  {"id":218,"lujin1":"文学艺术","lujin2":"热销TOP30","imgurl":"img/wenxue8.jpg","imgurl2":"img/wenxuelun8.jpg","xiangqingtu":"img/wenxuetu8.jpg","price":"29.90","prices":"59.80","title":"偏偏宠爱","zuozhe":"藤萝为枝","xiaoliang":"18346","kucun":"796","chubanshe":"青岛","chubanrqi":"2019-06-09"},
	  {"id":219,"lujin1":"文学艺术","lujin2":"热销TOP30","imgurl":"img/wenxue9.jpg","imgurl2":"img/wenxuelun9.jpg","xiangqingtu":"img/wenxuetu9.jpg","price":"59.60","prices":"298.00","title":"鲁迅经典全集(共10册)","zuozhe":"鲁迅","xiaoliang":"20545","kucun":"887","chubanshe":"中国文史","chubanrqi":"2018-06-10"},
	  {"id":220,"lujin1":"文学艺术","lujin2":"热销TOP30","imgurl":"img/wenxue10.jpg","imgurl2":"img/wenxuelun10.jpg","xiangqingtu":"img/wenxuetu10.jpg","price":"119.00","prices":"328.00","title":"鲁迅作品（全10册）","zuozhe":"鲁迅","xiaoliang":"1391","kucun":"139","chubanshe":"民主与建设","chubanrqi":"2020-07-14"},
	  {"id":221,"lujin1":"文学艺术","lujin2":"热销TOP30","imgurl":"img/wenxue11.jpg","imgurl2":"img/wenxuelun11.jpg","xiangqingtu":"img/wenxuetu11.jpg","price":"42.82","prices":"192.00","title":"浪漫古典行（全六册）","zuozhe":"蕴玉","xiaoliang":"1789","kucun":"128","chubanshe":"中国华侨","chubanrqi":"2018-03-17"},
	  {"id":222,"lujin1":"文学艺术","lujin2":"热销TOP30","imgurl":"img/wenxue12.jpg","imgurl2":"img/wenxuelun12.jpg","xiangqingtu":"img/wenxuetu12.jpg","price":"50.75","prices":"72.00","title":"长征 上下2册","zuozhe":"王树增","xiaoliang":"4907","kucun":"384","chubanshe":"人民文学","chubanrqi":"2020-09-21"},
	  {"id":223,"lujin1":"文学艺术","lujin2":"热销TOP30","imgurl":"img/wenxue13.jpg","imgurl2":"img/wenxuelun13.jpg","xiangqingtu":"img/wenxuetu13.jpg","price":"13.76","prices":"25.00","title":"罗生门","zuozhe":"(日)芥川龙之介","xiaoliang":"43954","kucun":"288","chubanshe":"吉林出版集团","chubanrqi":"2019-02-18"},
	  {"id":224,"lujin1":"文学艺术","lujin2":"热销TOP30","imgurl":"img/wenxue14.jpg","imgurl2":"img/wenxuelun14.jpg","xiangqingtu":"img/wenxuetu14.jpg","price":"32.89","prices":"50.60","title":"水浒传原著 上下共2册","zuozhe":"施耐庵","xiaoliang":"52655","kucun":"1858","chubanshe":"人民文学","chubanrqi":"2018-06-24"},
	  {"id":225,"lujin1":"文学艺术","lujin2":"热销TOP30","imgurl":"img/wenxue15.jpg","imgurl2":"img/wenxuelun15.jpg","xiangqingtu":"img/wenxuetu15.jpg","price":"17.50","prices":"36.00","title":"银河帝国1基地 七年级下","zuozhe":"(美)艾萨克·阿西莫夫","xiaoliang":"93048","kucun":"1634","chubanshe":"江苏文艺","chubanrqi":"2019-03-15"},
	  {"id":226,"lujin1":"文学艺术","lujin2":"热销TOP30","imgurl":"img/wenxue16.jpg","imgurl2":"img/wenxuelun16.jpg","xiangqingtu":"img/wenxuetu16.jpg","price":"26.00","prices":"40.00","title":"俗世奇人(共2册)","zuozhe":"冯骥才","xiaoliang":"30769","kucun":"1985","chubanshe":"浙江文学","chubanrqi":"2019-04-12"},
	  {"id":227,"lujin1":"文学艺术","lujin2":"热销TOP30","imgurl":"img/wenxue17.jpg","imgurl2":"img/wenxuelun17.jpg","xiangqingtu":"img/wenxuetu17.jpg","price":"19.00","prices":"38.00","title":"流浪地球","zuozhe":"刘慈欣","xiaoliang":"6362","kucun":"1382","chubanshe":"中国华侨","chubanrqi":"2020-09-17"},
	  {"id":228,"lujin1":"文学艺术","lujin2":"热销TOP30","imgurl":"img/wenxue18.jpg","imgurl2":"img/wenxuelun18.jpg","xiangqingtu":"img/wenxuetu18.jpg","price":"29.80","prices":"39.80","title":"平凡的世界 八年级","zuozhe":"路遥","xiaoliang":"58649","kucun":"679","chubanshe":"北京十月文艺","chubanrqi":"2019-03-18"},
	  {"id":229,"lujin1":"文学艺术","lujin2":"热销TOP30","imgurl":"img/wenxue19.jpg","imgurl2":"img/wenxuelun19.jpg","xiangqingtu":"img/wenxuetu19.jpg","price":"28.50","prices":"38.00","title":"苏菲的世界","zuozhe":"(挪威)乔斯坦·贾德","xiaoliang":"52810","kucun":"7315","chubanshe":"作家","chubanrqi":"2018-03-19"},
	  {"id":230,"lujin1":"文学艺术","lujin2":"热销TOP30","imgurl":"img/wenxue20.jpg","imgurl2":"img/wenxuelun20.jpg","xiangqingtu":"img/wenxuetu20.jpg","price":"21.87","prices":"36.00","title":"七年级阅读 红岩","zuozhe":"罗广斌","xiaoliang":"132714","kucun":"8712","chubanshe":"中国青年","chubanrqi":"2019-12-12"},
	  {"id":231,"lujin1":"文学艺术","lujin2":"热销TOP30","imgurl":"img/wenxue21.jpg","imgurl2":"img/wenxuelun21.jpg","xiangqingtu":"img/wenxuetu21.jpg","price":"112.10","prices":"151.80","title":"杀破狼（共3册）","zuozhe":"PRIEST","xiaoliang":"5803","kucun":"279","chubanshe":"湖南文艺","chubanrqi":"2018-02-12"},
	  {"id":232,"lujin1":"文学艺术","lujin2":"热销TOP30","imgurl":"img/wenxue22.jpg","imgurl2":"img/wenxuelun22.jpg","xiangqingtu":"img/wenxuetu22.jpg","price":"38.50","prices":"55.00","title":"人生海海","zuozhe":"麦家","xiaoliang":"13879","kucun":"1168","chubanshe":"北京十月文艺","chubanrqi":"2020-04-21"},
	  {"id":233,"lujin1":"文学艺术","lujin2":"热销TOP30","imgurl":"img/wenxue23.jpg","imgurl2":"img/wenxuelun23.jpg","xiangqingtu":"img/wenxuetu23.jpg","price":"41.30","prices":"59.00","title":"文城 余华新书","zuozhe":"余华","xiaoliang":"37890","kucun":"5886","chubanshe":"北京十月文艺","chubanrqi":"2019-02-15"},
	  {"id":234,"lujin1":"文学艺术","lujin2":"热销TOP30","imgurl":"img/wenxue24.jpg","imgurl2":"img/wenxuelun24.jpg","xiangqingtu":"img/wenxuetu24.jpg","price":"41.31","prices":"59.00","title":"你当像鸟飞往你的山","zuozhe":"塔拉·韦斯特弗","xiaoliang":"57279","kucun":"7189","chubanshe":"南海","chubanrqi":"2020-09-12"},
	  {"id":235,"lujin1":"文学艺术","lujin2":"热销TOP30","imgurl":"img/wenxue25.jpg","imgurl2":"img/wenxuelun25.jpg","xiangqingtu":"img/wenxuetu25.jpg","price":"29.40","prices":"49.00","title":"心安即是归处","zuozhe":"季羡林","xiaoliang":"767","kucun":"320","chubanshe":"古吴轩","chubanrqi":"2018-02-15"},
	  {"id":236,"lujin1":"文学艺术","lujin2":"热销TOP30","imgurl":"img/wenxue26.jpg","imgurl2":"img/wenxuelun26.jpg","xiangqingtu":"img/wenxuetu26.jpg","price":"46.68","prices":"93.00","title":"三体（1-3 共3册）","zuozhe":"刘慈欣","xiaoliang":"455304","kucun":"2724","chubanshe":"重庆","chubanrqi":"2019-11-23"},
	  {"id":237,"lujin1":"文学艺术","lujin2":"热销TOP30","imgurl":"img/wenxue27.jpg","imgurl2":"img/wenxuelun27.jpg","xiangqingtu":"img/wenxuetu27.jpg","price":"24.50","prices":"35.00","title":"活着","zuozhe":"余华","xiaoliang":"60149","kucun":"4494","chubanshe":"北京文艺","chubanrqi":"2020-11-14"},
	  {"id":238,"lujin1":"文学艺术","lujin2":"热销TOP30","imgurl":"img/wenxue28.jpg","imgurl2":"img/wenxuelun28.jpg","xiangqingtu":"img/wenxuetu28.jpg","price":"48.33","prices":"69.00","title":"霍乱时期的爱情","zuozhe":"马尔克斯","xiaoliang":"19564","kucun":"1867","chubanshe":"南海","chubanrqi":"2018-02-07"},
	  {"id":239,"lujin1":"文学艺术","lujin2":"热销TOP30","imgurl":"img/wenxue29.jpg","imgurl2":"img/wenxuelun29.jpg","xiangqingtu":"img/wenxuetu29.jpg","price":"34.00","prices":"68.00","title":"克拉拉与太阳(精)","zuozhe":"(英)石黑一雄","xiaoliang":"7057","kucun":"823","chubanshe":"上海译文","chubanrqi":"2020-09-18"},
	  {"id":240,"lujin1":"文学艺术","lujin2":"热销TOP30","imgurl":"img/wenxue30.jpg","imgurl2":"img/wenxuelun30.jpg","xiangqingtu":"img/wenxuetu30.jpg","price":"37.00","prices":"49.80","title":"人民的正义","zuozhe":"余飞","xiaoliang":"1887","kucun":"185","chubanshe":"东方","chubanrqi":"2019-08-14"}
	    ]
}